{"problem":{"A":[{"cost":35.0,"dst":12,"src":1,"toll":false},{"cost":35.0,"dst":16,"src":1,"toll":false},{"cost":6.032874584197998,"dst":25,"src":1,"toll":false},{"cost":14.06576919555664,"dst":34,"src":1,"toll":true},{"cost":35.0,"dst":135,"src":1,"toll":false},{"cost":35.0,"dst":10,"src":2,"toll":false},{"cost":17.5,"dst":26,"src":2,"toll":true},{"cost":19.55255126953125,"dst":57,"src":2,"toll":false},{"cost":10.877082824707031,"dst":61,"src":2,"toll":false},{"cost":14.363006591796875,"dst":80,"src":2,"toll":true},{"cost":35.0,"dst":137,"src":2,"toll":false},{"cost":30.293794631958008,"dst":141,"src":2,"toll":false},{"cost":7.800071716308594,"dst":20,"src":3,"toll":false},{"cost":16.416208267211914,"dst":31,"src":3,"toll":false},{"cost":9.390053749084473,"dst":49,"src":3,"toll":false},{"cost":25.150279998779297,"dst":113,"src":3,"toll":false},{"cost":4.0051984786987305,"dst":131,"src":3,"toll":true},{"cost":22.879274368286133,"dst":133,"src":3,"toll":false},{"cost":22.745891571044922,"dst":8,"src":4,"toll":false},{"cost":27.047250747680664,"dst":37,"src":4,"toll":false},{"cost":18.905366897583008,"dst":57,"src":4,"toll":false},{"cost":6.250289440155029,"dst":130,"src":4,"toll":false},{"cost":31.634550094604492,"dst":7,"src":5,"toll":false},{"cost":12.647383689880371,"dst":44,"src":5,"toll":true},{"cost":19.289020538330078,"dst":45,"src":5,"toll":false},{"cost":35.0,"dst":73,"src":5,"toll":false},{"cost":4.4526591300964355,"dst":93,"src":5,"toll":true},{"cost":18.4749755859375,"dst":13,"src":6,"toll":false},{"cost":35.0,"dst":26,"src":6,"toll":false},{"cost":34.77543640136719,"dst":63,"src":6,"toll":false},{"cost":35.0,"dst":116,"src":6,"toll":false},{"cost":12.720806121826172,"dst":141,"src":6,"toll":false},{"cost":31.634550094604492,"dst":5,"src":7,"toll":false},{"cost":14.783987998962402,"dst":12,"src":7,"toll":false},{"cost":29.083768844604492,"dst":45,"src":7,"toll":false},{"cost":5.973031044006348,"dst":93,"src":7,"toll":true},{"cost":30.315099716186523,"dst":143,"src":7,"toll":false},{"cost":22.745891571044922,"dst":4,"src":8,"toll":false},{"cost":20.21404266357422,"dst":17,"src":8,"toll":false},{"cost":13.400227546691895,"dst":37,"src":8,"toll":true},{"cost":25.997426986694336,"dst":130,"src":8,"toll":false},{"cost":9.001319885253906,"dst":139,"src":8,"toll":false},{"cost":24.569263458251953,"dst":21,"src":9,"toll":false},{"cost":6.799163341522217,"dst":32,"src":9,"toll":true},{"cost":35.0,"dst":47,"src":9,"toll":false},{"cost":5.524543762207031,"dst":59,"src":9,"toll":true},{"cost":12.971246719360352,"dst":80,"src":9,"toll":true},{"cost":13.18706226348877,"dst":85,"src":9,"toll":false},{"cost":30.991920471191406,"dst":86,"src":9,"toll":false},{"cost":6.465368747711182,"dst":108,"src":9,"toll":false},{"cost":23.653047561645508,"dst":111,"src":9,"toll":false},{"cost":35.0,"dst":138,"src":9,"toll":false},{"cost":35.0,"dst":2,"src":10,"toll":false},{"cost":32.908653259277344,"dst":57,"src":10,"toll":false},{"cost":26.63217544555664,"dst":130,"src":10,"toll":false},{"cost":17.5,"dst":137,"src":10,"toll":true},{"cost":35.0,"dst":46,"src":11,"toll":false},{"cost":7.992746829986572,"dst":54,"src":11,"toll":true},{"cost":26.2713680267334,"dst":55,"src":11,"toll":false},{"cost":7.951938629150391,"dst":66,"src":11,"toll":false},{"cost":35.0,"dst":1,"src":12,"toll":false},{"cost":14.783987998962402,"dst":7,"src":12,"toll":false},{"cost":29.162551879882813,"dst":25,"src":12,"toll":false},{"cost":23.534902572631836,"dst":93,"src":12,"toll":false},{"cost":20.76970863342285,"dst":135,"src":12,"toll":false},{"cost":32.394378662109375,"dst":140,"src":12,"toll":false},{"cost":20.623146057128906,"dst":143,"src":12,"toll":false},{"cost":18.4749755859375,"dst":6,"src":13,"toll":false},{"cost":5.942784309387207,"dst":26,"src":13,"toll":true},{"cost":19.902942657470703,"dst":80,"src":13,"toll":false},{"cost":35.0,"dst":116,"src":13,"toll":false},{"cost":16.38333511352539,"dst":122,"src":13,"toll":false},{"cost":33.38899230957031,"dst":70,"src":14,"toll":false},{"cost":31.197328567504883,"dst":71,"src":14,"toll":false},{"cost":30.79442596435547,"dst":92,"src":14,"toll":false},{"cost":18.602558135986328,"dst":121,"src":14,"toll":false},{"cost":3.163501739501953,"dst":128,"src":14,"toll":true},{"cost":25.444034576416016,"dst":132,"src":14,"toll":false},{"cost":4.581818103790283,"dst":142,"src":14,"toll":true},{"cost":32.682064056396484,"dst":76,"src":15,"toll":false},{"cost":8.956435203552246,"dst":78,"src":15,"toll":false},{"cost":31.11627769470215,"dst":97,"src":15,"toll":false},{"cost":31.1417293548584,"dst":109,"src":15,"toll":false},{"cost":22.742422103881836,"dst":140,"src":15,"toll":false},{"cost":35.0,"dst":1,"src":16,"toll":false},{"cost":12.332704544067383,"dst":34,"src":16,"toll":false},{"cost":35.0,"dst":36,"src":16,"toll":false},{"cost":19.4428768157959,"dst":78,"src":16,"toll":false},{"cost":6.209111213684082,"dst":135,"src":16,"toll":false},{"cost":20.21404266357422,"dst":8,"src":17,"toll":false},{"cost":31.067276000976563,"dst":20,"src":17,"toll":false},{"cost":14.656322479248047,"dst":22,"src":17,"toll":false},{"cost":15.077744483947754,"dst":47,"src":17,"toll":false},{"cost":15.1666259765625,"dst":67,"src":17,"toll":false},{"cost":26.040576934814453,"dst":101,"src":17,"toll":false},{"cost":30.945852279663086,"dst":129,"src":17,"toll":false},{"cost":15.141733169555664,"dst":130,"src":17,"toll":false},{"cost":17.361671447753906,"dst":133,"src":17,"toll":false},{"cost":30.691556930541992,"dst":139,"src":17,"toll":false},{"cost":18.81778335571289,"dst":30,"src":18,"toll":false},{"cost":35.0,"dst":48,"src":18,"toll":false},{"cost":13.56005859375,"dst":70,"src":18,"toll":false},{"cost":28.34583854675293,"dst":75,"src":18,"toll":false},{"cost":35.0,"dst":117,"src":18,"toll":false},{"cost":32.42989730834961,"dst":40,"src":19,"toll":false},{"cost":17.5,"dst":51,"src":19,"toll":true},{"cost":33.56951904296875,"dst":68,"src":19,"toll":false},{"cost":12.630145072937012,"dst":90,"src":19,"toll":false},{"cost":11.144039154052734,"dst":115,"src":19,"toll":false},{"cost":35.0,"dst":136,"src":19,"toll":false},{"cost":7.800071716308594,"dst":3,"src":20,"toll":false},{"cost":31.067276000976563,"dst":17,"src":20,"toll":false},{"cost":35.0,"dst":37,"src":20,"toll":false},{"cost":33.004119873046875,"dst":67,"src":20,"toll":false},{"cost":19.83566665649414,"dst":109,"src":20,"toll":false},{"cost":4.582327842712402,"dst":113,"src":20,"toll":true},{"cost":35.0,"dst":133,"src":20,"toll":false},{"cost":24.569263458251953,"dst":9,"src":21,"toll":false},{"cost":33.80282974243164,"dst":80,"src":21,"toll":false},{"cost":24.732940673828125,"dst":122,"src":21,"toll":false},{"cost":35.0,"dst":123,"src":21,"toll":false},{"cost":31.824560165405273,"dst":138,"src":21,"toll":false},{"cost":14.656322479248047,"dst":17,"src":22,"toll":false},{"cost":35.0,"dst":37,"src":22,"toll":false},{"cost":15.024699211120605,"dst":67,"src":22,"toll":true},{"cost":13.521027565002441,"dst":129,"src":22,"toll":false},{"cost":10.896756172180176,"dst":139,"src":22,"toll":false},{"cost":25.915388107299805,"dst":33,"src":23,"toll":false},{"cost":19.88935089111328,"dst":39,"src":23,"toll":false},{"cost":26.907390594482422,"dst":48,"src":23,"toll":false},{"cost":29.642288208007813,"dst":50,"src":23,"toll":false},{"cost":22.971967697143555,"dst":79,"src":23,"toll":false},{"cost":31.571325302124023,"dst":82,"src":23,"toll":false},{"cost":35.0,"dst":83,"src":23,"toll":false},{"cost":34.002296447753906,"dst":99,"src":23,"toll":false},{"cost":17.5,"dst":25,"src":24,"toll":true},{"cost":19.016000747680664,"dst":51,"src":24,"toll":false},{"cost":29.585472106933594,"dst":62,"src":24,"toll":false},{"cost":3.942720413208008,"dst":64,"src":24,"toll":true},{"cost":3.551302909851074,"dst":110,"src":24,"toll":true},{"cost":4.936143398284912,"dst":115,"src":24,"toll":true},{"cost":3.345207452774048,"dst":120,"src":24,"toll":true},{"cost":6.032874584197998,"dst":1,"src":25,"toll":false},{"cost":29.162551879882813,"dst":12,"src":25,"toll":false},{"cost":17.5,"dst":24,"src":25,"toll":true},{"cost":35.0,"dst":34,"src":25,"toll":false},{"cost":35.0,"dst":53,"src":25,"toll":false},{"cost":26.473878860473633,"dst":62,"src":25,"toll":false},{"cost":11.56638240814209,"dst":120,"src":25,"toll":true},{"cost":7.6600823402404785,"dst":143,"src":25,"toll":true},{"cost":17.5,"dst":2,"src":26,"toll":true},{"cost":35.0,"dst":6,"src":26,"toll":false},{"cost":5.942784309387207,"dst":13,"src":26,"toll":true},{"cost":4.707536697387695,"dst":80,"src":26,"toll":true},{"cost":3.8192028999328613,"dst":141,"src":26,"toll":true},{"cost":17.5,"dst":35,"src":27,"toll":true},{"cost":18.76729965209961,"dst":54,"src":27,"toll":false},{"cost":19.56365203857422,"dst":72,"src":27,"toll":false},{"cost":35.0,"dst":81,"src":27,"toll":false},{"cost":3.7448136806488037,"dst":124,"src":27,"toll":true},{"cost":13.344264030456543,"dst":104,"src":28,"toll":false},{"cost":33.96849822998047,"dst":128,"src":28,"toll":false},{"cost":35.0,"dst":142,"src":28,"toll":false},{"cost":5.471172332763672,"dst":43,"src":29,"toll":false},{"cost":10.520057678222656,"dst":55,"src":29,"toll":false},{"cost":28.977190017700195,"dst":63,"src":29,"toll":false},{"cost":16.43536376953125,"dst":72,"src":29,"toll":true},{"cost":35.0,"dst":141,"src":29,"toll":false},{"cost":18.81778335571289,"dst":18,"src":30,"toll":false},{"cost":20.186664581298828,"dst":40,"src":30,"toll":false},{"cost":35.0,"dst":48,"src":30,"toll":false},{"cost":35.0,"dst":102,"src":30,"toll":false},{"cost":18.952665328979492,"dst":117,"src":30,"toll":false},{"cost":16.416208267211914,"dst":3,"src":31,"toll":false},{"cost":9.091377258300781,"dst":47,"src":31,"toll":false},{"cost":35.0,"dst":49,"src":31,"toll":false},{"cost":5.010953903198242,"dst":52,"src":31,"toll":false},{"cost":35.0,"dst":101,"src":31,"toll":false},{"cost":26.348228454589844,"dst":133,"src":31,"toll":false},{"cost":6.799163341522217,"dst":9,"src":32,"toll":true},{"cost":6.243943214416504,"dst":34,"src":32,"toll":true},{"cost":7.632976055145264,"dst":56,"src":32,"toll":true},{"cost":29.658985137939453,"dst":85,"src":32,"toll":false},{"cost":15.439665794372559,"dst":96,"src":32,"toll":false},{"cost":21.8420467376709,"dst":111,"src":32,"toll":false},{"cost":2.7475194931030273,"dst":120,"src":32,"toll":true},{"cost":11.922195434570313,"dst":131,"src":32,"toll":true},{"cost":25.915388107299805,"dst":23,"src":33,"toll":false},{"cost":22.387279510498047,"dst":50,"src":33,"toll":false},{"cost":22.921279907226563,"dst":66,"src":33,"toll":false},{"cost":35.0,"dst":83,"src":33,"toll":false},{"cost":6.724404811859131,"dst":89,"src":33,"toll":true},{"cost":5.972622871398926,"dst":134,"src":33,"toll":true},{"cost":14.06576919555664,"dst":1,"src":34,"toll":true},{"cost":12.332704544067383,"dst":16,"src":34,"toll":false},{"cost":35.0,"dst":25,"src":34,"toll":false},{"cost":6.243943214416504,"dst":32,"src":34,"toll":true},{"cost":5.396120071411133,"dst":36,"src":34,"toll":false},{"cost":15.853169441223145,"dst":56,"src":34,"toll":false},{"cost":4.805349349975586,"dst":120,"src":34,"toll":true},{"cost":17.5,"dst":27,"src":35,"toll":true},{"cost":17.5,"dst":63,"src":35,"toll":true},{"cost":8.325492858886719,"dst":72,"src":35,"toll":false},{"cost":35.0,"dst":124,"src":35,"toll":false},{"cost":35.0,"dst":16,"src":36,"toll":false},{"cost":5.396120071411133,"dst":34,"src":36,"toll":false},{"cost":6.553439140319824,"dst":56,"src":36,"toll":false},{"cost":9.993721008300781,"dst":76,"src":36,"toll":false},{"cost":18.053733825683594,"dst":78,"src":36,"toll":false},{"cost":27.047250747680664,"dst":4,"src":37,"toll":false},{"cost":13.400227546691895,"dst":8,"src":37,"toll":true},{"cost":35.0,"dst":20,"src":37,"toll":false},{"cost":35.0,"dst":22,"src":37,"toll":false},{"cost":35.0,"dst":57,"src":37,"toll":false},{"cost":30.07172966003418,"dst":61,"src":37,"toll":false},{"cost":35.0,"dst":67,"src":37,"toll":false},{"cost":12.362473487854004,"dst":139,"src":37,"toll":false},{"cost":6.893960475921631,"dst":141,"src":37,"toll":true},{"cost":4.977773189544678,"dst":77,"src":38,"toll":true},{"cost":7.032665252685547,"dst":79,"src":38,"toll":true},{"cost":23.80839729309082,"dst":82,"src":38,"toll":false},{"cost":35.0,"dst":103,"src":38,"toll":false},{"cost":29.042369842529297,"dst":104,"src":38,"toll":false},{"cost":4.822661876678467,"dst":125,"src":38,"toll":true},{"cost":19.88935089111328,"dst":23,"src":39,"toll":false},{"cost":27.70339012145996,"dst":40,"src":39,"toll":false},{"cost":35.0,"dst":48,"src":39,"toll":false},{"cost":6.031060218811035,"dst":50,"src":39,"toll":false},{"cost":32.99407958984375,"dst":68,"src":39,"toll":false},{"cost":25.47083282470703,"dst":74,"src":39,"toll":false},{"cost":32.42989730834961,"dst":19,"src":40,"toll":false},{"cost":20.186664581298828,"dst":30,"src":40,"toll":false},{"cost":27.70339012145996,"dst":39,"src":40,"toll":false},{"cost":6.0438079833984375,"dst":48,"src":40,"toll":true},{"cost":6.4910712242126465,"dst":68,"src":40,"toll":false},{"cost":19.20757293701172,"dst":102,"src":40,"toll":false},{"cost":10.792075157165527,"dst":115,"src":40,"toll":true},{"cost":10.039212226867676,"dst":64,"src":41,"toll":false},{"cost":35.0,"dst":106,"src":41,"toll":false},{"cost":7.601487159729004,"dst":107,"src":41,"toll":false},{"cost":26.94408416748047,"dst":112,"src":41,"toll":false},{"cost":16.732196807861328,"dst":127,"src":41,"toll":true},{"cost":32.45983123779297,"dst":44,"src":42,"toll":false},{"cost":16.067237854003906,"dst":73,"src":42,"toll":false},{"cost":34.105899810791016,"dst":88,"src":42,"toll":false},{"cost":17.5,"dst":97,"src":42,"toll":true},{"cost":34.550724029541016,"dst":118,"src":42,"toll":false},{"cost":5.471172332763672,"dst":29,"src":43,"toll":false},{"cost":6.603150844573975,"dst":55,"src":43,"toll":true},{"cost":27.007919311523438,"dst":69,"src":43,"toll":false},{"cost":21.784509658813477,"dst":98,"src":43,"toll":false},{"cost":6.238608360290527,"dst":103,"src":43,"toll":true},{"cost":12.647383689880371,"dst":5,"src":44,"toll":true},{"cost":32.45983123779297,"dst":42,"src":44,"toll":false},{"cost":10.605162620544434,"dst":45,"src":44,"toll":true},{"cost":32.346824645996094,"dst":73,"src":44,"toll":false},{"cost":6.1009521484375,"dst":88,"src":44,"toll":true},{"cost":27.310274124145508,"dst":95,"src":44,"toll":false},{"cost":19.289020538330078,"dst":5,"src":45,"toll":false},{"cost":29.083768844604492,"dst":7,"src":45,"toll":false},{"cost":10.605162620544434,"dst":44,"src":45,"toll":true},{"cost":26.88387680053711,"dst":95,"src":45,"toll":false},{"cost":35.0,"dst":143,"src":45,"toll":false},{"cost":35.0,"dst":11,"src":46,"toll":false},{"cost":35.0,"dst":54,"src":46,"toll":false},{"cost":18.239290237426758,"dst":66,"src":46,"toll":false},{"cost":35.0,"dst":81,"src":46,"toll":false},{"cost":28.905059814453125,"dst":89,"src":46,"toll":false},{"cost":35.0,"dst":9,"src":47,"toll":false},{"cost":15.077744483947754,"dst":17,"src":47,"toll":false},{"cost":9.091377258300781,"dst":31,"src":47,"toll":false},{"cost":5.873114585876465,"dst":52,"src":47,"toll":false},{"cost":35.0,"dst":86,"src":47,"toll":false},{"cost":35.0,"dst":101,"src":47,"toll":false},{"cost":8.545178413391113,"dst":108,"src":47,"toll":true},{"cost":2.7197265625,"dst":130,"src":47,"toll":true},{"cost":35.0,"dst":18,"src":48,"toll":false},{"cost":26.907390594482422,"dst":23,"src":48,"toll":false},{"cost":35.0,"dst":30,"src":48,"toll":false},{"cost":35.0,"dst":39,"src":48,"toll":false},{"cost":6.0438079833984375,"dst":40,"src":48,"toll":true},{"cost":35.0,"dst":75,"src":48,"toll":false},{"cost":15.33466625213623,"dst":82,"src":48,"toll":false},{"cost":4.075870513916016,"dst":125,"src":48,"toll":true},{"cost":9.390053749084473,"dst":3,"src":49,"toll":false},{"cost":35.0,"dst":31,"src":49,"toll":false},{"cost":30.94979476928711,"dst":52,"src":49,"toll":false},{"cost":25.800710678100586,"dst":85,"src":49,"toll":false},{"cost":26.37934684753418,"dst":131,"src":49,"toll":false},{"cost":29.642288208007813,"dst":23,"src":50,"toll":false},{"cost":22.387279510498047,"dst":33,"src":50,"toll":false},{"cost":6.031060218811035,"dst":39,"src":50,"toll":false},{"cost":18.096282958984375,"dst":74,"src":50,"toll":false},{"cost":26.420169830322266,"dst":89,"src":50,"toll":false},{"cost":25.616174697875977,"dst":91,"src":50,"toll":false},{"cost":17.5,"dst":19,"src":51,"toll":true},{"cost":19.016000747680664,"dst":24,"src":51,"toll":false},{"cost":33.92338562011719,"dst":90,"src":51,"toll":false},{"cost":7.919915199279785,"dst":115,"src":51,"toll":false},{"cost":9.656129837036133,"dst":120,"src":51,"toll":false},{"cost":5.010953903198242,"dst":31,"src":52,"toll":false},{"cost":5.873114585876465,"dst":47,"src":52,"toll":false},{"cost":30.94979476928711,"dst":49,"src":52,"toll":false},{"cost":17.498611450195313,"dst":85,"src":52,"toll":false},{"cost":35.0,"dst":108,"src":52,"toll":false},{"cost":35.0,"dst":25,"src":53,"toll":false},{"cost":28.3316650390625,"dst":62,"src":53,"toll":false},{"cost":35.0,"dst":105,"src":53,"toll":false},{"cost":28.37274742126465,"dst":143,"src":53,"toll":false},{"cost":7.992746829986572,"dst":11,"src":54,"toll":true},{"cost":18.76729965209961,"dst":27,"src":54,"toll":false},{"cost":35.0,"dst":46,"src":54,"toll":false},{"cost":35.0,"dst":55,"src":54,"toll":false},{"cost":25.72606658935547,"dst":72,"src":54,"toll":false},{"cost":16.309242248535156,"dst":81,"src":54,"toll":false},{"cost":26.2713680267334,"dst":11,"src":55,"toll":false},{"cost":10.520057678222656,"dst":29,"src":55,"toll":false},{"cost":6.603150844573975,"dst":43,"src":55,"toll":true},{"cost":35.0,"dst":54,"src":55,"toll":false},{"cost":22.775951385498047,"dst":66,"src":55,"toll":false},{"cost":24.472593307495117,"dst":72,"src":55,"toll":false},{"cost":35.0,"dst":98,"src":55,"toll":false},{"cost":13.606473922729492,"dst":134,"src":55,"toll":false},{"cost":7.632976055145264,"dst":32,"src":56,"toll":true},{"cost":15.853169441223145,"dst":34,"src":56,"toll":false},{"cost":6.553439140319824,"dst":36,"src":56,"toll":false},{"cost":4.831114768981934,"dst":76,"src":56,"toll":true},{"cost":18.41730499267578,"dst":113,"src":56,"toll":false},{"cost":9.416666030883789,"dst":131,"src":56,"toll":false},{"cost":19.55255126953125,"dst":2,"src":57,"toll":false},{"cost":18.905366897583008,"dst":4,"src":57,"toll":false},{"cost":32.908653259277344,"dst":10,"src":57,"toll":false},{"cost":35.0,"dst":37,"src":57,"toll":false},{"cost":29.473329544067383,"dst":61,"src":57,"toll":false},{"cost":31.847341537475586,"dst":130,"src":57,"toll":false},{"cost":33.2218017578125,"dst":65,"src":58,"toll":false},{"cost":13.144623756408691,"dst":73,"src":58,"toll":false},{"cost":8.12710189819336,"dst":93,"src":58,"toll":true},{"cost":6.240753173828125,"dst":97,"src":58,"toll":true},{"cost":7.552750110626221,"dst":140,"src":58,"toll":false},{"cost":5.524543762207031,"dst":9,"src":59,"toll":true},{"cost":35.0,"dst":84,"src":59,"toll":false},{"cost":19.861236572265625,"dst":96,"src":59,"toll":false},{"cost":10.554923057556152,"dst":111,"src":59,"toll":true},{"cost":3.3244481086730957,"dst":138,"src":59,"toll":true},{"cost":22.391082763671875,"dst":116,"src":60,"toll":false},{"cost":17.5,"dst":119,"src":60,"toll":true},{"cost":7.610456466674805,"dst":124,"src":60,"toll":false},{"cost":31.55866241455078,"dst":126,"src":60,"toll":false},{"cost":10.877082824707031,"dst":2,"src":61,"toll":false},{"cost":30.07172966003418,"dst":37,"src":61,"toll":false},{"cost":29.473329544067383,"dst":57,"src":61,"toll":false},{"cost":17.5,"dst":141,"src":61,"toll":true},{"cost":29.585472106933594,"dst":24,"src":62,"toll":false},{"cost":26.473878860473633,"dst":25,"src":62,"toll":false},{"cost":28.3316650390625,"dst":53,"src":62,"toll":false},{"cost":34.731414794921875,"dst":64,"src":62,"toll":false},{"cost":22.739845275878906,"dst":87,"src":62,"toll":false},{"cost":19.20010757446289,"dst":88,"src":62,"toll":false},{"cost":30.996620178222656,"dst":105,"src":62,"toll":false},{"cost":34.77543640136719,"dst":6,"src":63,"toll":false},{"cost":28.977190017700195,"dst":29,"src":63,"toll":false},{"cost":17.5,"dst":35,"src":63,"toll":true},{"cost":35.0,"dst":72,"src":63,"toll":false},{"cost":35.0,"dst":116,"src":63,"toll":false},{"cost":29.581937789916992,"dst":124,"src":63,"toll":false},{"cost":8.551919937133789,"dst":141,"src":63,"toll":true},{"cost":3.942720413208008,"dst":24,"src":64,"toll":true},{"cost":10.039212226867676,"dst":41,"src":64,"toll":false},{"cost":34.731414794921875,"dst":62,"src":64,"toll":false},{"cost":15.136188507080078,"dst":88,"src":64,"toll":true},{"cost":8.943008422851563,"dst":106,"src":64,"toll":true},{"cost":35.0,"dst":110,"src":64,"toll":false},{"cost":12.9032621383667,"dst":112,"src":64,"toll":false},{"cost":33.2218017578125,"dst":58,"src":65,"toll":false},{"cost":19.11148452758789,"dst":73,"src":65,"toll":false},{"cost":8.208454132080078,"dst":97,"src":65,"toll":false},{"cost":27.422317504882813,"dst":118,"src":65,"toll":false},{"cost":7.951938629150391,"dst":11,"src":66,"toll":false},{"cost":22.921279907226563,"dst":33,"src":66,"toll":false},{"cost":18.239290237426758,"dst":46,"src":66,"toll":false},{"cost":22.775951385498047,"dst":55,"src":66,"toll":false},{"cost":34.612030029296875,"dst":89,"src":66,"toll":false},{"cost":11.395915985107422,"dst":134,"src":66,"toll":false},{"cost":15.1666259765625,"dst":17,"src":67,"toll":false},{"cost":33.004119873046875,"dst":20,"src":67,"toll":false},{"cost":15.024699211120605,"dst":22,"src":67,"toll":true},{"cost":35.0,"dst":37,"src":67,"toll":false},{"cost":25.578426361083984,"dst":129,"src":67,"toll":false},{"cost":33.56951904296875,"dst":19,"src":68,"toll":false},{"cost":32.99407958984375,"dst":39,"src":68,"toll":false},{"cost":6.4910712242126465,"dst":40,"src":68,"toll":false},{"cost":34.09540557861328,"dst":74,"src":68,"toll":false},{"cost":19.79481315612793,"dst":84,"src":68,"toll":false},{"cost":34.272369384765625,"dst":136,"src":68,"toll":false},{"cost":27.007919311523438,"dst":43,"src":69,"toll":false},{"cost":17.68699836730957,"dst":83,"src":69,"toll":false},{"cost":33.51772689819336,"dst":98,"src":69,"toll":false},{"cost":12.084802627563477,"dst":103,"src":69,"toll":false},{"cost":35.0,"dst":134,"src":69,"toll":false},{"cost":33.38899230957031,"dst":14,"src":70,"toll":false},{"cost":13.56005859375,"dst":18,"src":70,"toll":false},{"cost":23.46019172668457,"dst":75,"src":70,"toll":false},{"cost":35.0,"dst":77,"src":70,"toll":false},{"cost":10.381175994873047,"dst":117,"src":70,"toll":false},{"cost":21.130022048950195,"dst":121,"src":70,"toll":false},{"cost":20.211589813232422,"dst":142,"src":70,"toll":false},{"cost":31.197328567504883,"dst":14,"src":71,"toll":false},{"cost":35.0,"dst":100,"src":71,"toll":false},{"cost":32.04960632324219,"dst":117,"src":71,"toll":false},{"cost":35.0,"dst":121,"src":71,"toll":false},{"cost":6.056535243988037,"dst":127,"src":71,"toll":false},{"cost":27.33127784729004,"dst":132,"src":71,"toll":false},{"cost":15.457525253295898,"dst":144,"src":71,"toll":false},{"cost":19.56365203857422,"dst":27,"src":72,"toll":false},{"cost":16.43536376953125,"dst":29,"src":72,"toll":true},{"cost":8.325492858886719,"dst":35,"src":72,"toll":false},{"cost":25.72606658935547,"dst":54,"src":72,"toll":false},{"cost":24.472593307495117,"dst":55,"src":72,"toll":false},{"cost":35.0,"dst":63,"src":72,"toll":false},{"cost":35.0,"dst":5,"src":73,"toll":false},{"cost":16.067237854003906,"dst":42,"src":73,"toll":false},{"cost":32.346824645996094,"dst":44,"src":73,"toll":false},{"cost":13.144623756408691,"dst":58,"src":73,"toll":false},{"cost":19.11148452758789,"dst":65,"src":73,"toll":false},{"cost":6.446516990661621,"dst":93,"src":73,"toll":false},{"cost":30.46861457824707,"dst":118,"src":73,"toll":false},{"cost":25.47083282470703,"dst":39,"src":74,"toll":false},{"cost":18.096282958984375,"dst":50,"src":74,"toll":false},{"cost":34.09540557861328,"dst":68,"src":74,"toll":false},{"cost":25.383750915527344,"dst":84,"src":74,"toll":false},{"cost":16.399911880493164,"dst":91,"src":74,"toll":false},{"cost":28.34583854675293,"dst":18,"src":75,"toll":false},{"cost":35.0,"dst":48,"src":75,"toll":false},{"cost":23.46019172668457,"dst":70,"src":75,"toll":false},{"cost":11.35584545135498,"dst":77,"src":75,"toll":false},{"cost":33.631553649902344,"dst":125,"src":75,"toll":false},{"cost":32.682064056396484,"dst":15,"src":76,"toll":false},{"cost":9.993721008300781,"dst":36,"src":76,"toll":false},{"cost":4.831114768981934,"dst":56,"src":76,"toll":true},{"cost":26.18443489074707,"dst":78,"src":76,"toll":false},{"cost":3.12870192527771,"dst":109,"src":76,"toll":true},{"cost":16.199851989746094,"dst":113,"src":76,"toll":false},{"cost":4.977773189544678,"dst":38,"src":77,"toll":true},{"cost":35.0,"dst":70,"src":77,"toll":false},{"cost":11.35584545135498,"dst":75,"src":77,"toll":false},{"cost":11.786874771118164,"dst":104,"src":77,"toll":false},{"cost":21.302845001220703,"dst":125,"src":77,"toll":false},{"cost":13.728431701660156,"dst":142,"src":77,"toll":false},{"cost":8.956435203552246,"dst":15,"src":78,"toll":false},{"cost":19.4428768157959,"dst":16,"src":78,"toll":false},{"cost":18.053733825683594,"dst":36,"src":78,"toll":false},{"cost":26.18443489074707,"dst":76,"src":78,"toll":false},{"cost":29.912961959838867,"dst":135,"src":78,"toll":false},{"cost":35.0,"dst":140,"src":78,"toll":false},{"cost":22.971967697143555,"dst":23,"src":79,"toll":false},{"cost":7.032665252685547,"dst":38,"src":79,"toll":true},{"cost":35.0,"dst":82,"src":79,"toll":false},{"cost":8.569064140319824,"dst":94,"src":79,"toll":false},{"cost":6.367061614990234,"dst":99,"src":79,"toll":true},{"cost":3.0943350791931152,"dst":103,"src":79,"toll":true},{"cost":14.363006591796875,"dst":2,"src":80,"toll":true},{"cost":12.971246719360352,"dst":9,"src":80,"toll":true},{"cost":19.902942657470703,"dst":13,"src":80,"toll":false},{"cost":33.80282974243164,"dst":21,"src":80,"toll":false},{"cost":4.707536697387695,"dst":26,"src":80,"toll":true},{"cost":5.482669830322266,"dst":86,"src":80,"toll":true},{"cost":16.675682067871094,"dst":122,"src":80,"toll":true},{"cost":23.80937957763672,"dst":137,"src":80,"toll":false},{"cost":35.0,"dst":27,"src":81,"toll":false},{"cost":35.0,"dst":46,"src":81,"toll":false},{"cost":16.309242248535156,"dst":54,"src":81,"toll":false},{"cost":15.163677215576172,"dst":89,"src":81,"toll":false},{"cost":35.0,"dst":119,"src":81,"toll":false},{"cost":28.734031677246094,"dst":123,"src":81,"toll":false},{"cost":6.470676898956299,"dst":124,"src":81,"toll":true},{"cost":35.0,"dst":126,"src":81,"toll":false},{"cost":17.5,"dst":138,"src":81,"toll":true},{"cost":31.571325302124023,"dst":23,"src":82,"toll":false},{"cost":23.80839729309082,"dst":38,"src":82,"toll":false},{"cost":15.33466625213623,"dst":48,"src":82,"toll":false},{"cost":35.0,"dst":79,"src":82,"toll":false},{"cost":22.611907958984375,"dst":125,"src":82,"toll":false},{"cost":35.0,"dst":23,"src":83,"toll":false},{"cost":35.0,"dst":33,"src":83,"toll":false},{"cost":17.68699836730957,"dst":69,"src":83,"toll":false},{"cost":31.54804039001465,"dst":99,"src":83,"toll":false},{"cost":35.0,"dst":103,"src":83,"toll":false},{"cost":9.058511734008789,"dst":134,"src":83,"toll":true},{"cost":35.0,"dst":59,"src":84,"toll":false},{"cost":19.79481315612793,"dst":68,"src":84,"toll":false},{"cost":25.383750915527344,"dst":74,"src":84,"toll":false},{"cost":28.570947647094727,"dst":91,"src":84,"toll":false},{"cost":11.590502738952637,"dst":96,"src":84,"toll":true},{"cost":30.25,"dst":114,"src":84,"toll":false},{"cost":31.647092819213867,"dst":136,"src":84,"toll":false},{"cost":13.319541931152344,"dst":138,"src":84,"toll":false},{"cost":13.18706226348877,"dst":9,"src":85,"toll":false},{"cost":29.658985137939453,"dst":32,"src":85,"toll":false},{"cost":25.800710678100586,"dst":49,"src":85,"toll":false},{"cost":17.498611450195313,"dst":52,"src":85,"toll":false},{"cost":5.47365665435791,"dst":108,"src":85,"toll":false},{"cost":15.05968189239502,"dst":131,"src":85,"toll":true},{"cost":30.991920471191406,"dst":9,"src":86,"toll":false},{"cost":35.0,"dst":47,"src":86,"toll":false},{"cost":5.482669830322266,"dst":80,"src":86,"toll":true},{"cost":2.776793956756592,"dst":130,"src":86,"toll":true},{"cost":35.0,"dst":137,"src":86,"toll":false},{"cost":22.739845275878906,"dst":62,"src":87,"toll":false},{"cost":11.979351043701172,"dst":88,"src":87,"toll":false},{"cost":17.5,"dst":95,"src":87,"toll":true},{"cost":31.433422088623047,"dst":105,"src":87,"toll":false},{"cost":34.105899810791016,"dst":42,"src":88,"toll":false},{"cost":6.1009521484375,"dst":44,"src":88,"toll":true},{"cost":19.20010757446289,"dst":62,"src":88,"toll":false},{"cost":15.136188507080078,"dst":64,"src":88,"toll":true},{"cost":11.979351043701172,"dst":87,"src":88,"toll":false},{"cost":8.117998123168945,"dst":95,"src":88,"toll":false},{"cost":11.061214447021484,"dst":112,"src":88,"toll":true},{"cost":33.62474822998047,"dst":132,"src":88,"toll":false},{"cost":6.724404811859131,"dst":33,"src":89,"toll":true},{"cost":28.905059814453125,"dst":46,"src":89,"toll":false},{"cost":26.420169830322266,"dst":50,"src":89,"toll":false},{"cost":34.612030029296875,"dst":66,"src":89,"toll":false},{"cost":15.163677215576172,"dst":81,"src":89,"toll":false},{"cost":9.838211059570313,"dst":91,"src":89,"toll":false},{"cost":15.210489273071289,"dst":138,"src":89,"toll":true},{"cost":12.630145072937012,"dst":19,"src":90,"toll":false},{"cost":33.92338562011719,"dst":51,"src":90,"toll":false},{"cost":33.508995056152344,"dst":114,"src":90,"toll":false},{"cost":27.385948181152344,"dst":120,"src":90,"toll":false},{"cost":12.390201568603516,"dst":136,"src":90,"toll":false},{"cost":25.616174697875977,"dst":50,"src":91,"toll":false},{"cost":16.399911880493164,"dst":74,"src":91,"toll":false},{"cost":28.570947647094727,"dst":84,"src":91,"toll":false},{"cost":9.838211059570313,"dst":89,"src":91,"toll":false},{"cost":21.273422241210938,"dst":138,"src":91,"toll":false},{"cost":30.79442596435547,"dst":14,"src":92,"toll":false},{"cost":32.07027816772461,"dst":128,"src":92,"toll":false},{"cost":11.246671676635742,"dst":132,"src":92,"toll":false},{"cost":4.4526591300964355,"dst":5,"src":93,"toll":true},{"cost":5.973031044006348,"dst":7,"src":93,"toll":true},{"cost":23.534902572631836,"dst":12,"src":93,"toll":false},{"cost":8.12710189819336,"dst":58,"src":93,"toll":true},{"cost":6.446516990661621,"dst":73,"src":93,"toll":false},{"cost":9.154468536376953,"dst":140,"src":93,"toll":false},{"cost":8.569064140319824,"dst":79,"src":94,"toll":false},{"cost":15.616133689880371,"dst":99,"src":94,"toll":false},{"cost":14.636255264282227,"dst":103,"src":94,"toll":false},{"cost":27.310274124145508,"dst":44,"src":95,"toll":false},{"cost":26.88387680053711,"dst":45,"src":95,"toll":false},{"cost":17.5,"dst":87,"src":95,"toll":true},{"cost":8.117998123168945,"dst":88,"src":95,"toll":false},{"cost":17.235851287841797,"dst":105,"src":95,"toll":false},{"cost":27.88344955444336,"dst":143,"src":95,"toll":false},{"cost":15.439665794372559,"dst":32,"src":96,"toll":false},{"cost":19.861236572265625,"dst":59,"src":96,"toll":false},{"cost":11.590502738952637,"dst":84,"src":96,"toll":true},{"cost":35.0,"dst":111,"src":96,"toll":false},{"cost":28.83392906188965,"dst":114,"src":96,"toll":false},{"cost":14.37457275390625,"dst":120,"src":96,"toll":false},{"cost":31.11627769470215,"dst":15,"src":97,"toll":false},{"cost":17.5,"dst":42,"src":97,"toll":true},{"cost":6.240753173828125,"dst":58,"src":97,"toll":true},{"cost":8.208454132080078,"dst":65,"src":97,"toll":false},{"cost":4.582261085510254,"dst":109,"src":97,"toll":true},{"cost":35.0,"dst":118,"src":97,"toll":false},{"cost":22.182987213134766,"dst":140,"src":97,"toll":false},{"cost":21.784509658813477,"dst":43,"src":98,"toll":false},{"cost":35.0,"dst":55,"src":98,"toll":false},{"cost":33.51772689819336,"dst":69,"src":98,"toll":false},{"cost":23.242095947265625,"dst":134,"src":98,"toll":false},{"cost":34.002296447753906,"dst":23,"src":99,"toll":false},{"cost":6.367061614990234,"dst":79,"src":99,"toll":true},{"cost":31.54804039001465,"dst":83,"src":99,"toll":false},{"cost":15.616133689880371,"dst":94,"src":99,"toll":false},{"cost":10.697336196899414,"dst":103,"src":99,"toll":false},{"cost":35.0,"dst":71,"src":100,"toll":false},{"cost":29.759069442749023,"dst":102,"src":100,"toll":false},{"cost":8.108014106750488,"dst":106,"src":100,"toll":false},{"cost":28.29911994934082,"dst":110,"src":100,"toll":false},{"cost":23.665184020996094,"dst":117,"src":100,"toll":false},{"cost":19.061702728271484,"dst":144,"src":100,"toll":false},{"cost":26.040576934814453,"dst":17,"src":101,"toll":false},{"cost":35.0,"dst":31,"src":101,"toll":false},{"cost":35.0,"dst":47,"src":101,"toll":false},{"cost":22.758487701416016,"dst":133,"src":101,"toll":false},{"cost":35.0,"dst":30,"src":102,"toll":false},{"cost":19.20757293701172,"dst":40,"src":102,"toll":false},{"cost":29.759069442749023,"dst":100,"src":102,"toll":false},{"cost":29.208702087402344,"dst":110,"src":102,"toll":false},{"cost":32.1174201965332,"dst":115,"src":102,"toll":false},{"cost":35.0,"dst":117,"src":102,"toll":false},{"cost":35.0,"dst":38,"src":103,"toll":false},{"cost":6.238608360290527,"dst":43,"src":103,"toll":true},{"cost":12.084802627563477,"dst":69,"src":103,"toll":false},{"cost":3.0943350791931152,"dst":79,"src":103,"toll":true},{"cost":35.0,"dst":83,"src":103,"toll":false},{"cost":14.636255264282227,"dst":94,"src":103,"toll":false},{"cost":10.697336196899414,"dst":99,"src":103,"toll":false},{"cost":13.344264030456543,"dst":28,"src":104,"toll":false},{"cost":29.042369842529297,"dst":38,"src":104,"toll":false},{"cost":11.786874771118164,"dst":77,"src":104,"toll":false},{"cost":14.41906452178955,"dst":142,"src":104,"toll":false},{"cost":35.0,"dst":53,"src":105,"toll":false},{"cost":30.996620178222656,"dst":62,"src":105,"toll":false},{"cost":31.433422088623047,"dst":87,"src":105,"toll":false},{"cost":17.235851287841797,"dst":95,"src":105,"toll":false},{"cost":28.73301124572754,"dst":143,"src":105,"toll":false},{"cost":35.0,"dst":41,"src":106,"toll":false},{"cost":8.943008422851563,"dst":64,"src":106,"toll":true},{"cost":8.108014106750488,"dst":100,"src":106,"toll":false},{"cost":35.0,"dst":110,"src":106,"toll":false},{"cost":10.842570304870605,"dst":127,"src":106,"toll":false},{"cost":6.635109901428223,"dst":144,"src":106,"toll":false},{"cost":7.601487159729004,"dst":41,"src":107,"toll":false},{"cost":35.0,"dst":112,"src":107,"toll":false},{"cost":26.83264923095703,"dst":127,"src":107,"toll":false},{"cost":17.842565536499023,"dst":132,"src":107,"toll":false},{"cost":6.465368747711182,"dst":9,"src":108,"toll":false},{"cost":8.545178413391113,"dst":47,"src":108,"toll":true},{"cost":35.0,"dst":52,"src":108,"toll":false},{"cost":5.47365665435791,"dst":85,"src":108,"toll":false},{"cost":31.1417293548584,"dst":15,"src":109,"toll":false},{"cost":19.83566665649414,"dst":20,"src":109,"toll":false},{"cost":3.12870192527771,"dst":76,"src":109,"toll":true},{"cost":4.582261085510254,"dst":97,"src":109,"toll":true},{"cost":2.8598923683166504,"dst":113,"src":109,"toll":true},{"cost":3.551302909851074,"dst":24,"src":110,"toll":true},{"cost":35.0,"dst":64,"src":110,"toll":false},{"cost":28.29911994934082,"dst":100,"src":110,"toll":false},{"cost":29.208702087402344,"dst":102,"src":110,"toll":false},{"cost":35.0,"dst":106,"src":110,"toll":false},{"cost":22.81564712524414,"dst":115,"src":110,"toll":false},{"cost":23.653047561645508,"dst":9,"src":111,"toll":false},{"cost":21.8420467376709,"dst":32,"src":111,"toll":false},{"cost":10.554923057556152,"dst":59,"src":111,"toll":true},{"cost":35.0,"dst":96,"src":111,"toll":false},{"cost":26.94408416748047,"dst":41,"src":112,"toll":false},{"cost":12.9032621383667,"dst":64,"src":112,"toll":false},{"cost":11.061214447021484,"dst":88,"src":112,"toll":true},{"cost":35.0,"dst":107,"src":112,"toll":false},{"cost":9.943954467773438,"dst":132,"src":112,"toll":false},{"cost":25.150279998779297,"dst":3,"src":113,"toll":false},{"cost":4.582327842712402,"dst":20,"src":113,"toll":true},{"cost":18.41730499267578,"dst":56,"src":113,"toll":false},{"cost":16.199851989746094,"dst":76,"src":113,"toll":false},{"cost":2.8598923683166504,"dst":109,"src":113,"toll":true},{"cost":3.4260456562042236,"dst":131,"src":113,"toll":true},{"cost":30.25,"dst":84,"src":114,"toll":false},{"cost":33.508995056152344,"dst":90,"src":114,"toll":false},{"cost":28.83392906188965,"dst":96,"src":114,"toll":false},{"cost":11.794380187988281,"dst":120,"src":114,"toll":true},{"cost":17.5,"dst":136,"src":114,"toll":true},{"cost":11.144039154052734,"dst":19,"src":115,"toll":false},{"cost":4.936143398284912,"dst":24,"src":115,"toll":true},{"cost":10.792075157165527,"dst":40,"src":115,"toll":true},{"cost":7.919915199279785,"dst":51,"src":115,"toll":false},{"cost":32.1174201965332,"dst":102,"src":115,"toll":false},{"cost":22.81564712524414,"dst":110,"src":115,"toll":false},{"cost":35.0,"dst":6,"src":116,"toll":false},{"cost":35.0,"dst":13,"src":116,"toll":false},{"cost":22.391082763671875,"dst":60,"src":116,"toll":false},{"cost":35.0,"dst":63,"src":116,"toll":false},{"cost":27.66427993774414,"dst":119,"src":116,"toll":false},{"cost":31.50839614868164,"dst":122,"src":116,"toll":false},{"cost":13.440796852111816,"dst":124,"src":116,"toll":false},{"cost":35.0,"dst":18,"src":117,"toll":false},{"cost":18.952665328979492,"dst":30,"src":117,"toll":false},{"cost":10.381175994873047,"dst":70,"src":117,"toll":false},{"cost":32.04960632324219,"dst":71,"src":117,"toll":false},{"cost":23.665184020996094,"dst":100,"src":117,"toll":false},{"cost":35.0,"dst":102,"src":117,"toll":false},{"cost":16.103919982910156,"dst":121,"src":117,"toll":false},{"cost":34.550724029541016,"dst":42,"src":118,"toll":false},{"cost":27.422317504882813,"dst":65,"src":118,"toll":false},{"cost":30.46861457824707,"dst":73,"src":118,"toll":false},{"cost":35.0,"dst":97,"src":118,"toll":false},{"cost":17.5,"dst":60,"src":119,"toll":true},{"cost":35.0,"dst":81,"src":119,"toll":false},{"cost":27.66427993774414,"dst":116,"src":119,"toll":false},{"cost":25.646656036376953,"dst":122,"src":119,"toll":false},{"cost":17.535236358642578,"dst":123,"src":119,"toll":false},{"cost":25.55562400817871,"dst":126,"src":119,"toll":false},{"cost":3.345207452774048,"dst":24,"src":120,"toll":true},{"cost":11.56638240814209,"dst":25,"src":120,"toll":true},{"cost":2.7475194931030273,"dst":32,"src":120,"toll":true},{"cost":4.805349349975586,"dst":34,"src":120,"toll":true},{"cost":9.656129837036133,"dst":51,"src":120,"toll":false},{"cost":27.385948181152344,"dst":90,"src":120,"toll":false},{"cost":14.37457275390625,"dst":96,"src":120,"toll":false},{"cost":11.794380187988281,"dst":114,"src":120,"toll":true},{"cost":18.602558135986328,"dst":14,"src":121,"toll":false},{"cost":21.130022048950195,"dst":70,"src":121,"toll":false},{"cost":35.0,"dst":71,"src":121,"toll":false},{"cost":16.103919982910156,"dst":117,"src":121,"toll":false},{"cost":16.38333511352539,"dst":13,"src":122,"toll":false},{"cost":24.732940673828125,"dst":21,"src":122,"toll":false},{"cost":16.675682067871094,"dst":80,"src":122,"toll":true},{"cost":31.50839614868164,"dst":116,"src":122,"toll":false},{"cost":25.646656036376953,"dst":119,"src":122,"toll":false},{"cost":7.993166923522949,"dst":123,"src":122,"toll":false},{"cost":35.0,"dst":21,"src":123,"toll":false},{"cost":28.734031677246094,"dst":81,"src":123,"toll":false},{"cost":17.535236358642578,"dst":119,"src":123,"toll":false},{"cost":7.993166923522949,"dst":122,"src":123,"toll":false},{"cost":11.864811897277832,"dst":138,"src":123,"toll":false},{"cost":3.7448136806488037,"dst":27,"src":124,"toll":true},{"cost":35.0,"dst":35,"src":124,"toll":false},{"cost":7.610456466674805,"dst":60,"src":124,"toll":false},{"cost":29.581937789916992,"dst":63,"src":124,"toll":false},{"cost":6.470676898956299,"dst":81,"src":124,"toll":true},{"cost":13.440796852111816,"dst":116,"src":124,"toll":false},{"cost":24.628089904785156,"dst":126,"src":124,"toll":false},{"cost":4.822661876678467,"dst":38,"src":125,"toll":true},{"cost":4.075870513916016,"dst":48,"src":125,"toll":true},{"cost":33.631553649902344,"dst":75,"src":125,"toll":false},{"cost":21.302845001220703,"dst":77,"src":125,"toll":false},{"cost":22.611907958984375,"dst":82,"src":125,"toll":false},{"cost":31.55866241455078,"dst":60,"src":126,"toll":false},{"cost":35.0,"dst":81,"src":126,"toll":false},{"cost":25.55562400817871,"dst":119,"src":126,"toll":false},{"cost":24.628089904785156,"dst":124,"src":126,"toll":false},{"cost":16.732196807861328,"dst":41,"src":127,"toll":true},{"cost":6.056535243988037,"dst":71,"src":127,"toll":false},{"cost":10.842570304870605,"dst":106,"src":127,"toll":false},{"cost":26.83264923095703,"dst":107,"src":127,"toll":false},{"cost":26.00433349609375,"dst":132,"src":127,"toll":false},{"cost":8.727875709533691,"dst":144,"src":127,"toll":false},{"cost":3.163501739501953,"dst":14,"src":128,"toll":true},{"cost":33.96849822998047,"dst":28,"src":128,"toll":false},{"cost":32.07027816772461,"dst":92,"src":128,"toll":false},{"cost":25.060653686523438,"dst":142,"src":128,"toll":false},{"cost":30.945852279663086,"dst":17,"src":129,"toll":false},{"cost":13.521027565002441,"dst":22,"src":129,"toll":false},{"cost":25.578426361083984,"dst":67,"src":129,"toll":false},{"cost":6.250289440155029,"dst":4,"src":130,"toll":false},{"cost":25.997426986694336,"dst":8,"src":130,"toll":false},{"cost":26.63217544555664,"dst":10,"src":130,"toll":false},{"cost":15.141733169555664,"dst":17,"src":130,"toll":false},{"cost":2.7197265625,"dst":47,"src":130,"toll":true},{"cost":31.847341537475586,"dst":57,"src":130,"toll":false},{"cost":2.776793956756592,"dst":86,"src":130,"toll":true},{"cost":31.25749969482422,"dst":137,"src":130,"toll":false},{"cost":4.0051984786987305,"dst":3,"src":131,"toll":true},{"cost":11.922195434570313,"dst":32,"src":131,"toll":true},{"cost":26.37934684753418,"dst":49,"src":131,"toll":false},{"cost":9.416666030883789,"dst":56,"src":131,"toll":false},{"cost":15.05968189239502,"dst":85,"src":131,"toll":true},{"cost":3.4260456562042236,"dst":113,"src":131,"toll":true},{"cost":25.444034576416016,"dst":14,"src":132,"toll":false},{"cost":27.33127784729004,"dst":71,"src":132,"toll":false},{"cost":33.62474822998047,"dst":88,"src":132,"toll":false},{"cost":11.246671676635742,"dst":92,"src":132,"toll":false},{"cost":17.842565536499023,"dst":107,"src":132,"toll":false},{"cost":9.943954467773438,"dst":112,"src":132,"toll":false},{"cost":26.00433349609375,"dst":127,"src":132,"toll":false},{"cost":22.879274368286133,"dst":3,"src":133,"toll":false},{"cost":17.361671447753906,"dst":17,"src":133,"toll":false},{"cost":35.0,"dst":20,"src":133,"toll":false},{"cost":26.348228454589844,"dst":31,"src":133,"toll":false},{"cost":22.758487701416016,"dst":101,"src":133,"toll":false},{"cost":5.972622871398926,"dst":33,"src":134,"toll":true},{"cost":13.606473922729492,"dst":55,"src":134,"toll":false},{"cost":11.395915985107422,"dst":66,"src":134,"toll":false},{"cost":35.0,"dst":69,"src":134,"toll":false},{"cost":9.058511734008789,"dst":83,"src":134,"toll":true},{"cost":23.242095947265625,"dst":98,"src":134,"toll":false},{"cost":35.0,"dst":1,"src":135,"toll":false},{"cost":20.76970863342285,"dst":12,"src":135,"toll":false},{"cost":6.209111213684082,"dst":16,"src":135,"toll":false},{"cost":29.912961959838867,"dst":78,"src":135,"toll":false},{"cost":22.28742027282715,"dst":140,"src":135,"toll":false},{"cost":35.0,"dst":19,"src":136,"toll":false},{"cost":34.272369384765625,"dst":68,"src":136,"toll":false},{"cost":31.647092819213867,"dst":84,"src":136,"toll":false},{"cost":12.390201568603516,"dst":90,"src":136,"toll":false},{"cost":17.5,"dst":114,"src":136,"toll":true},{"cost":35.0,"dst":2,"src":137,"toll":false},{"cost":17.5,"dst":10,"src":137,"toll":true},{"cost":23.80937957763672,"dst":80,"src":137,"toll":false},{"cost":35.0,"dst":86,"src":137,"toll":false},{"cost":31.25749969482422,"dst":130,"src":137,"toll":false},{"cost":35.0,"dst":9,"src":138,"toll":false},{"cost":31.824560165405273,"dst":21,"src":138,"toll":false},{"cost":3.3244481086730957,"dst":59,"src":138,"toll":true},{"cost":17.5,"dst":81,"src":138,"toll":true},{"cost":13.319541931152344,"dst":84,"src":138,"toll":false},{"cost":15.210489273071289,"dst":89,"src":138,"toll":true},{"cost":21.273422241210938,"dst":91,"src":138,"toll":false},{"cost":11.864811897277832,"dst":123,"src":138,"toll":false},{"cost":9.001319885253906,"dst":8,"src":139,"toll":false},{"cost":30.691556930541992,"dst":17,"src":139,"toll":false},{"cost":10.896756172180176,"dst":22,"src":139,"toll":false},{"cost":12.362473487854004,"dst":37,"src":139,"toll":false},{"cost":32.394378662109375,"dst":12,"src":140,"toll":false},{"cost":22.742422103881836,"dst":15,"src":140,"toll":false},{"cost":7.552750110626221,"dst":58,"src":140,"toll":false},{"cost":35.0,"dst":78,"src":140,"toll":false},{"cost":9.154468536376953,"dst":93,"src":140,"toll":false},{"cost":22.182987213134766,"dst":97,"src":140,"toll":false},{"cost":22.28742027282715,"dst":135,"src":140,"toll":false},{"cost":30.293794631958008,"dst":2,"src":141,"toll":false},{"cost":12.720806121826172,"dst":6,"src":141,"toll":false},{"cost":3.8192028999328613,"dst":26,"src":141,"toll":true},{"cost":35.0,"dst":29,"src":141,"toll":false},{"cost":6.893960475921631,"dst":37,"src":141,"toll":true},{"cost":17.5,"dst":61,"src":141,"toll":true},{"cost":8.551919937133789,"dst":63,"src":141,"toll":true},{"cost":4.581818103790283,"dst":14,"src":142,"toll":true},{"cost":35.0,"dst":28,"src":142,"toll":false},{"cost":20.211589813232422,"dst":70,"src":142,"toll":false},{"cost":13.728431701660156,"dst":77,"src":142,"toll":false},{"cost":14.41906452178955,"dst":104,"src":142,"toll":false},{"cost":25.060653686523438,"dst":128,"src":142,"toll":false},{"cost":30.315099716186523,"dst":7,"src":143,"toll":false},{"cost":20.623146057128906,"dst":12,"src":143,"toll":false},{"cost":7.6600823402404785,"dst":25,"src":143,"toll":true},{"cost":35.0,"dst":45,"src":143,"toll":false},{"cost":28.37274742126465,"dst":53,"src":143,"toll":false},{"cost":27.88344955444336,"dst":95,"src":143,"toll":false},{"cost":28.73301124572754,"dst":105,"src":143,"toll":false},{"cost":15.457525253295898,"dst":71,"src":144,"toll":false},{"cost":19.061702728271484,"dst":100,"src":144,"toll":false},{"cost":6.635109901428223,"dst":106,"src":144,"toll":false},{"cost":8.727875709533691,"dst":127,"src":144,"toll":false}],"K":[{"demand":28.05398178100586,"dest":83,"index":1,"orig":27},{"demand":78.08993530273438,"dest":119,"index":2,"orig":129},{"demand":39.62844467163086,"dest":64,"index":3,"orig":55},{"demand":25.169891357421875,"dest":45,"index":4,"orig":125},{"demand":86.3955307006836,"dest":100,"index":5,"orig":39},{"demand":43.298099517822266,"dest":22,"index":6,"orig":58},{"demand":46.56995391845703,"dest":59,"index":7,"orig":123},{"demand":71.73188018798828,"dest":27,"index":8,"orig":44},{"demand":47.25631332397461,"dest":35,"index":9,"orig":143},{"demand":43.85708236694336,"dest":35,"index":10,"orig":120},{"demand":52.583351135253906,"dest":101,"index":11,"orig":108},{"demand":12.079788208007813,"dest":116,"index":12,"orig":27},{"demand":30.03702735900879,"dest":99,"index":13,"orig":143},{"demand":97.32209777832031,"dest":110,"index":14,"orig":80},{"demand":20.7080020904541,"dest":9,"index":15,"orig":55},{"demand":41.24059295654297,"dest":7,"index":16,"orig":113},{"demand":86.48916625976563,"dest":2,"index":17,"orig":80},{"demand":29.66410255432129,"dest":110,"index":18,"orig":43},{"demand":79.28886413574219,"dest":34,"index":19,"orig":35},{"demand":20.31555938720703,"dest":120,"index":20,"orig":133},{"demand":42.5491828918457,"dest":24,"index":21,"orig":23},{"demand":11.113166809082031,"dest":11,"index":22,"orig":103},{"demand":84.74711608886719,"dest":29,"index":23,"orig":128},{"demand":10.76699447631836,"dest":109,"index":24,"orig":80},{"demand":98.84165954589844,"dest":55,"index":25,"orig":18},{"demand":30.7109375,"dest":99,"index":26,"orig":51},{"demand":50.380088806152344,"dest":68,"index":27,"orig":138},{"demand":6.307535171508789,"dest":121,"index":28,"orig":21},{"demand":38.28493881225586,"dest":66,"index":29,"orig":7},{"demand":69.89524841308594,"dest":7,"index":30,"orig":112},{"demand":46.10896682739258,"dest":32,"index":31,"orig":27},{"demand":18.680294036865234,"dest":88,"index":32,"orig":7},{"demand":99.8056869506836,"dest":94,"index":33,"orig":79},{"demand":30.71306610107422,"dest":120,"index":34,"orig":2},{"demand":37.90220260620117,"dest":72,"index":35,"orig":46},{"demand":61.53943634033203,"dest":26,"index":36,"orig":116},{"demand":43.91496276855469,"dest":85,"index":37,"orig":93},{"demand":5.742339611053467,"dest":65,"index":38,"orig":83},{"demand":13.080519676208496,"dest":49,"index":39,"orig":14},{"demand":37.1550407409668,"dest":110,"index":40,"orig":127},{"demand":38.957862854003906,"dest":98,"index":41,"orig":138},{"demand":71.24665832519531,"dest":90,"index":42,"orig":3},{"demand":54.543575286865234,"dest":67,"index":43,"orig":89},{"demand":84.5903091430664,"dest":141,"index":44,"orig":140},{"demand":75.46375274658203,"dest":93,"index":45,"orig":135},{"demand":45.239322662353516,"dest":77,"index":46,"orig":78},{"demand":59.99970626831055,"dest":51,"index":47,"orig":59},{"demand":26.03294563293457,"dest":130,"index":48,"orig":35},{"demand":80.09439849853516,"dest":110,"index":49,"orig":114},{"demand":21.964988708496094,"dest":89,"index":50,"orig":97}],"V":144}}