{"problem":{"A":[{"cost":10.228607177734375,"dst":2,"src":1,"toll":false},{"cost":7.275785446166992,"dst":6,"src":1,"toll":false},{"cost":10.228607177734375,"dst":1,"src":2,"toll":false},{"cost":33.47385787963867,"dst":3,"src":2,"toll":false},{"cost":17.5,"dst":7,"src":2,"toll":true},{"cost":33.47385787963867,"dst":2,"src":3,"toll":false},{"cost":16.869876861572266,"dst":4,"src":3,"toll":true},{"cost":27.886754989624023,"dst":8,"src":3,"toll":false},{"cost":16.869876861572266,"dst":3,"src":4,"toll":true},{"cost":8.563506126403809,"dst":5,"src":4,"toll":false},{"cost":16.110137939453125,"dst":9,"src":4,"toll":false},{"cost":8.563506126403809,"dst":4,"src":5,"toll":false},{"cost":22.425048828125,"dst":10,"src":5,"toll":false},{"cost":7.275785446166992,"dst":1,"src":6,"toll":false},{"cost":35.0,"dst":7,"src":6,"toll":false},{"cost":26.515090942382813,"dst":11,"src":6,"toll":false},{"cost":17.5,"dst":2,"src":7,"toll":true},{"cost":35.0,"dst":6,"src":7,"toll":false},{"cost":9.5728120803833,"dst":8,"src":7,"toll":false},{"cost":27.123464584350586,"dst":12,"src":7,"toll":false},{"cost":27.886754989624023,"dst":3,"src":8,"toll":false},{"cost":9.5728120803833,"dst":7,"src":8,"toll":false},{"cost":19.8775691986084,"dst":9,"src":8,"toll":false},{"cost":18.142770767211914,"dst":13,"src":8,"toll":false},{"cost":16.110137939453125,"dst":4,"src":9,"toll":false},{"cost":19.8775691986084,"dst":8,"src":9,"toll":false},{"cost":35.0,"dst":10,"src":9,"toll":false},{"cost":10.859189987182617,"dst":14,"src":9,"toll":false},{"cost":22.425048828125,"dst":5,"src":10,"toll":false},{"cost":35.0,"dst":9,"src":10,"toll":false},{"cost":27.39385223388672,"dst":15,"src":10,"toll":false},{"cost":26.515090942382813,"dst":6,"src":11,"toll":false},{"cost":5.391729354858398,"dst":12,"src":11,"toll":false},{"cost":28.15650177001953,"dst":16,"src":11,"toll":false},{"cost":27.123464584350586,"dst":7,"src":12,"toll":false},{"cost":5.391729354858398,"dst":11,"src":12,"toll":false},{"cost":35.0,"dst":13,"src":12,"toll":false},{"cost":12.752625465393066,"dst":17,"src":12,"toll":false},{"cost":18.142770767211914,"dst":8,"src":13,"toll":false},{"cost":35.0,"dst":12,"src":13,"toll":false},{"cost":15.90826416015625,"dst":14,"src":13,"toll":true},{"cost":21.172199249267578,"dst":18,"src":13,"toll":false},{"cost":10.859189987182617,"dst":9,"src":14,"toll":false},{"cost":15.90826416015625,"dst":13,"src":14,"toll":true},{"cost":29.556842803955078,"dst":15,"src":14,"toll":false},{"cost":22.35589599609375,"dst":19,"src":14,"toll":false},{"cost":27.39385223388672,"dst":10,"src":15,"toll":false},{"cost":29.556842803955078,"dst":14,"src":15,"toll":false},{"cost":3.080139636993408,"dst":20,"src":15,"toll":true},{"cost":28.15650177001953,"dst":11,"src":16,"toll":false},{"cost":35.0,"dst":17,"src":16,"toll":false},{"cost":18.892995834350586,"dst":21,"src":16,"toll":false},{"cost":12.752625465393066,"dst":12,"src":17,"toll":false},{"cost":35.0,"dst":16,"src":17,"toll":false},{"cost":22.894376754760742,"dst":18,"src":17,"toll":false},{"cost":35.0,"dst":22,"src":17,"toll":false},{"cost":21.172199249267578,"dst":13,"src":18,"toll":false},{"cost":22.894376754760742,"dst":17,"src":18,"toll":false},{"cost":27.483692169189453,"dst":19,"src":18,"toll":false},{"cost":35.0,"dst":23,"src":18,"toll":false},{"cost":22.35589599609375,"dst":14,"src":19,"toll":false},{"cost":27.483692169189453,"dst":18,"src":19,"toll":false},{"cost":21.0057430267334,"dst":20,"src":19,"toll":false},{"cost":22.677743911743164,"dst":24,"src":19,"toll":false},{"cost":3.080139636993408,"dst":15,"src":20,"toll":true},{"cost":21.0057430267334,"dst":19,"src":20,"toll":false},{"cost":12.657779693603516,"dst":25,"src":20,"toll":false},{"cost":18.892995834350586,"dst":16,"src":21,"toll":false},{"cost":35.0,"dst":22,"src":21,"toll":false},{"cost":24.62088394165039,"dst":26,"src":21,"toll":false},{"cost":35.0,"dst":17,"src":22,"toll":false},{"cost":35.0,"dst":21,"src":22,"toll":false},{"cost":27.448720932006836,"dst":23,"src":22,"toll":false},{"cost":7.387879371643066,"dst":27,"src":22,"toll":true},{"cost":35.0,"dst":18,"src":23,"toll":false},{"cost":27.448720932006836,"dst":22,"src":23,"toll":false},{"cost":23.053653717041016,"dst":24,"src":23,"toll":false},{"cost":17.038131713867188,"dst":28,"src":23,"toll":false},{"cost":22.677743911743164,"dst":19,"src":24,"toll":false},{"cost":23.053653717041016,"dst":23,"src":24,"toll":false},{"cost":35.0,"dst":25,"src":24,"toll":false},{"cost":34.71820068359375,"dst":29,"src":24,"toll":false},{"cost":12.657779693603516,"dst":20,"src":25,"toll":false},{"cost":35.0,"dst":24,"src":25,"toll":false},{"cost":35.0,"dst":30,"src":25,"toll":false},{"cost":24.62088394165039,"dst":21,"src":26,"toll":false},{"cost":6.890361309051514,"dst":27,"src":26,"toll":true},{"cost":13.026253700256348,"dst":31,"src":26,"toll":false},{"cost":7.387879371643066,"dst":22,"src":27,"toll":true},{"cost":6.890361309051514,"dst":26,"src":27,"toll":true},{"cost":4.787545680999756,"dst":28,"src":27,"toll":true},{"cost":35.0,"dst":32,"src":27,"toll":false},{"cost":17.038131713867188,"dst":23,"src":28,"toll":false},{"cost":4.787545680999756,"dst":27,"src":28,"toll":true},{"cost":35.0,"dst":29,"src":28,"toll":false},{"cost":8.277854919433594,"dst":33,"src":28,"toll":true},{"cost":34.71820068359375,"dst":24,"src":29,"toll":false},{"cost":35.0,"dst":28,"src":29,"toll":false},{"cost":7.674309730529785,"dst":30,"src":29,"toll":true},{"cost":2.860755443572998,"dst":34,"src":29,"toll":true},{"cost":35.0,"dst":25,"src":30,"toll":false},{"cost":7.674309730529785,"dst":29,"src":30,"toll":true},{"cost":24.17300796508789,"dst":35,"src":30,"toll":false},{"cost":13.026253700256348,"dst":26,"src":31,"toll":false},{"cost":28.164535522460938,"dst":32,"src":31,"toll":false},{"cost":16.433156967163086,"dst":36,"src":31,"toll":false},{"cost":35.0,"dst":27,"src":32,"toll":false},{"cost":28.164535522460938,"dst":31,"src":32,"toll":false},{"cost":25.542251586914063,"dst":33,"src":32,"toll":false},{"cost":8.060853004455566,"dst":37,"src":32,"toll":false},{"cost":8.277854919433594,"dst":28,"src":33,"toll":true},{"cost":25.542251586914063,"dst":32,"src":33,"toll":false},{"cost":5.534528732299805,"dst":34,"src":33,"toll":true},{"cost":35.0,"dst":38,"src":33,"toll":false},{"cost":2.860755443572998,"dst":29,"src":34,"toll":true},{"cost":5.534528732299805,"dst":33,"src":34,"toll":true},{"cost":32.295013427734375,"dst":35,"src":34,"toll":false},{"cost":17.4635009765625,"dst":39,"src":34,"toll":true},{"cost":24.17300796508789,"dst":30,"src":35,"toll":false},{"cost":32.295013427734375,"dst":34,"src":35,"toll":false},{"cost":35.0,"dst":40,"src":35,"toll":false},{"cost":16.433156967163086,"dst":31,"src":36,"toll":false},{"cost":35.0,"dst":37,"src":36,"toll":false},{"cost":17.5,"dst":41,"src":36,"toll":true},{"cost":8.060853004455566,"dst":32,"src":37,"toll":false},{"cost":35.0,"dst":36,"src":37,"toll":false},{"cost":35.0,"dst":38,"src":37,"toll":false},{"cost":24.55345344543457,"dst":42,"src":37,"toll":false},{"cost":35.0,"dst":33,"src":38,"toll":false},{"cost":35.0,"dst":37,"src":38,"toll":false},{"cost":30.968019485473633,"dst":39,"src":38,"toll":false},{"cost":35.0,"dst":43,"src":38,"toll":false},{"cost":17.4635009765625,"dst":34,"src":39,"toll":true},{"cost":30.968019485473633,"dst":38,"src":39,"toll":false},{"cost":6.099041938781738,"dst":40,"src":39,"toll":true},{"cost":7.613420486450195,"dst":44,"src":39,"toll":true},{"cost":35.0,"dst":35,"src":40,"toll":false},{"cost":6.099041938781738,"dst":39,"src":40,"toll":true},{"cost":9.624065399169922,"dst":45,"src":40,"toll":true},{"cost":17.5,"dst":36,"src":41,"toll":true},{"cost":5.0704345703125,"dst":42,"src":41,"toll":false},{"cost":30.436635971069336,"dst":46,"src":41,"toll":false},{"cost":24.55345344543457,"dst":37,"src":42,"toll":false},{"cost":5.0704345703125,"dst":41,"src":42,"toll":false},{"cost":12.966329574584961,"dst":43,"src":42,"toll":false},{"cost":35.0,"dst":47,"src":42,"toll":false},{"cost":35.0,"dst":38,"src":43,"toll":false},{"cost":12.966329574584961,"dst":42,"src":43,"toll":false},{"cost":6.869400501251221,"dst":44,"src":43,"toll":false},{"cost":14.971030235290527,"dst":48,"src":43,"toll":true},{"cost":7.613420486450195,"dst":39,"src":44,"toll":true},{"cost":6.869400501251221,"dst":43,"src":44,"toll":false},{"cost":22.714635848999023,"dst":45,"src":44,"toll":false},{"cost":30.641075134277344,"dst":49,"src":44,"toll":false},{"cost":9.624065399169922,"dst":40,"src":45,"toll":true},{"cost":22.714635848999023,"dst":44,"src":45,"toll":false},{"cost":2.5582668781280518,"dst":50,"src":45,"toll":true},{"cost":30.436635971069336,"dst":41,"src":46,"toll":false},{"cost":16.849445343017578,"dst":47,"src":46,"toll":false},{"cost":30.07635498046875,"dst":51,"src":46,"toll":false},{"cost":35.0,"dst":42,"src":47,"toll":false},{"cost":16.849445343017578,"dst":46,"src":47,"toll":false},{"cost":30.940248489379883,"dst":48,"src":47,"toll":false},{"cost":34.391395568847656,"dst":52,"src":47,"toll":false},{"cost":14.971030235290527,"dst":43,"src":48,"toll":true},{"cost":30.940248489379883,"dst":47,"src":48,"toll":false},{"cost":35.0,"dst":49,"src":48,"toll":false},{"cost":7.8798980712890625,"dst":53,"src":48,"toll":false},{"cost":30.641075134277344,"dst":44,"src":49,"toll":false},{"cost":35.0,"dst":48,"src":49,"toll":false},{"cost":17.010162353515625,"dst":50,"src":49,"toll":false},{"cost":3.300518274307251,"dst":54,"src":49,"toll":true},{"cost":2.5582668781280518,"dst":45,"src":50,"toll":true},{"cost":17.010162353515625,"dst":49,"src":50,"toll":false},{"cost":12.42494010925293,"dst":55,"src":50,"toll":false},{"cost":30.07635498046875,"dst":46,"src":51,"toll":false},{"cost":9.25413703918457,"dst":52,"src":51,"toll":false},{"cost":29.95364761352539,"dst":56,"src":51,"toll":false},{"cost":34.391395568847656,"dst":47,"src":52,"toll":false},{"cost":9.25413703918457,"dst":51,"src":52,"toll":false},{"cost":2.55214786529541,"dst":53,"src":52,"toll":true},{"cost":22.477306365966797,"dst":57,"src":52,"toll":false},{"cost":7.8798980712890625,"dst":48,"src":53,"toll":false},{"cost":2.55214786529541,"dst":52,"src":53,"toll":true},{"cost":15.735855102539063,"dst":54,"src":53,"toll":false},{"cost":28.12946319580078,"dst":58,"src":53,"toll":false},{"cost":3.300518274307251,"dst":49,"src":54,"toll":true},{"cost":15.735855102539063,"dst":53,"src":54,"toll":false},{"cost":24.874858856201172,"dst":55,"src":54,"toll":false},{"cost":14.982073783874512,"dst":59,"src":54,"toll":false},{"cost":12.42494010925293,"dst":50,"src":55,"toll":false},{"cost":24.874858856201172,"dst":54,"src":55,"toll":false},{"cost":32.615196228027344,"dst":60,"src":55,"toll":false},{"cost":29.95364761352539,"dst":51,"src":56,"toll":false},{"cost":31.251502990722656,"dst":57,"src":56,"toll":false},{"cost":22.477306365966797,"dst":52,"src":57,"toll":false},{"cost":31.251502990722656,"dst":56,"src":57,"toll":false},{"cost":25.9549503326416,"dst":58,"src":57,"toll":false},{"cost":28.12946319580078,"dst":53,"src":58,"toll":false},{"cost":25.9549503326416,"dst":57,"src":58,"toll":false},{"cost":17.31618881225586,"dst":59,"src":58,"toll":true},{"cost":14.982073783874512,"dst":54,"src":59,"toll":false},{"cost":17.31618881225586,"dst":58,"src":59,"toll":true},{"cost":35.0,"dst":60,"src":59,"toll":false},{"cost":32.615196228027344,"dst":55,"src":60,"toll":false},{"cost":35.0,"dst":59,"src":60,"toll":false}],"K":[{"demand":22.278833389282227,"dest":33,"index":1,"orig":25},{"demand":82.70899200439453,"dest":31,"index":2,"orig":28},{"demand":60.44051742553711,"dest":50,"index":3,"orig":33},{"demand":96.95510864257813,"dest":3,"index":4,"orig":5},{"demand":21.67793083190918,"dest":48,"index":5,"orig":5},{"demand":95.76640319824219,"dest":32,"index":6,"orig":27},{"demand":99.40711975097656,"dest":37,"index":7,"orig":17},{"demand":51.22038269042969,"dest":30,"index":8,"orig":21},{"demand":75.25231170654297,"dest":30,"index":9,"orig":48},{"demand":68.68594360351563,"dest":26,"index":10,"orig":39},{"demand":89.37727355957031,"dest":39,"index":11,"orig":54},{"demand":29.729595184326172,"dest":52,"index":12,"orig":37},{"demand":14.613622665405273,"dest":50,"index":13,"orig":22},{"demand":26.35414695739746,"dest":29,"index":14,"orig":10},{"demand":52.51435852050781,"dest":59,"index":15,"orig":19},{"demand":48.1197624206543,"dest":16,"index":16,"orig":29},{"demand":51.26813888549805,"dest":59,"index":17,"orig":25},{"demand":72.97797393798828,"dest":34,"index":18,"orig":55},{"demand":29.962295532226563,"dest":33,"index":19,"orig":32},{"demand":10.671748161315918,"dest":40,"index":20,"orig":52},{"demand":81.38113403320313,"dest":32,"index":21,"orig":58},{"demand":70.55390167236328,"dest":10,"index":22,"orig":8},{"demand":5.538397312164307,"dest":56,"index":23,"orig":1},{"demand":19.151960372924805,"dest":56,"index":24,"orig":29},{"demand":48.95333480834961,"dest":26,"index":25,"orig":37},{"demand":79.11162567138672,"dest":49,"index":26,"orig":56},{"demand":80.27363586425781,"dest":13,"index":27,"orig":50},{"demand":48.988067626953125,"dest":8,"index":28,"orig":7},{"demand":11.672552108764648,"dest":42,"index":29,"orig":50},{"demand":17.01466941833496,"dest":37,"index":30,"orig":52},{"demand":1.3081610202789307,"dest":23,"index":31,"orig":47},{"demand":34.11603546142578,"dest":36,"index":32,"orig":19},{"demand":72.65277099609375,"dest":55,"index":33,"orig":2},{"demand":19.42559814453125,"dest":33,"index":34,"orig":20},{"demand":31.391883850097656,"dest":45,"index":35,"orig":5}],"V":60}}