{"problem":{"A":[{"cost":19.53927230834961,"dst":2,"src":1,"toll":false},{"cost":28.740447998046875,"dst":6,"src":1,"toll":false},{"cost":19.53927230834961,"dst":1,"src":2,"toll":false},{"cost":35.0,"dst":3,"src":2,"toll":false},{"cost":32.299888610839844,"dst":7,"src":2,"toll":false},{"cost":35.0,"dst":2,"src":3,"toll":false},{"cost":5.885115146636963,"dst":4,"src":3,"toll":false},{"cost":11.545425415039063,"dst":8,"src":3,"toll":false},{"cost":5.885115146636963,"dst":3,"src":4,"toll":false},{"cost":8.843355178833008,"dst":5,"src":4,"toll":true},{"cost":12.403579711914063,"dst":9,"src":4,"toll":false},{"cost":8.843355178833008,"dst":4,"src":5,"toll":true},{"cost":19.83468246459961,"dst":10,"src":5,"toll":false},{"cost":28.740447998046875,"dst":1,"src":6,"toll":false},{"cost":33.59239959716797,"dst":7,"src":6,"toll":false},{"cost":14.301469802856445,"dst":11,"src":6,"toll":true},{"cost":32.299888610839844,"dst":2,"src":7,"toll":false},{"cost":33.59239959716797,"dst":6,"src":7,"toll":false},{"cost":35.0,"dst":8,"src":7,"toll":false},{"cost":35.0,"dst":12,"src":7,"toll":false},{"cost":11.545425415039063,"dst":3,"src":8,"toll":false},{"cost":35.0,"dst":7,"src":8,"toll":false},{"cost":23.41478729248047,"dst":9,"src":8,"toll":false},{"cost":20.79252815246582,"dst":13,"src":8,"toll":false},{"cost":12.403579711914063,"dst":4,"src":9,"toll":false},{"cost":23.41478729248047,"dst":8,"src":9,"toll":false},{"cost":22.908231735229492,"dst":10,"src":9,"toll":false},{"cost":14.933906555175781,"dst":14,"src":9,"toll":false},{"cost":19.83468246459961,"dst":5,"src":10,"toll":false},{"cost":22.908231735229492,"dst":9,"src":10,"toll":false},{"cost":21.432605743408203,"dst":15,"src":10,"toll":false},{"cost":14.301469802856445,"dst":6,"src":11,"toll":true},{"cost":35.0,"dst":12,"src":11,"toll":false},{"cost":12.825233459472656,"dst":16,"src":11,"toll":false},{"cost":35.0,"dst":7,"src":12,"toll":false},{"cost":35.0,"dst":11,"src":12,"toll":false},{"cost":9.641273498535156,"dst":13,"src":12,"toll":false},{"cost":35.0,"dst":17,"src":12,"toll":false},{"cost":20.79252815246582,"dst":8,"src":13,"toll":false},{"cost":9.641273498535156,"dst":12,"src":13,"toll":false},{"cost":3.672914981842041,"dst":14,"src":13,"toll":true},{"cost":2.887437582015991,"dst":18,"src":13,"toll":true},{"cost":14.933906555175781,"dst":9,"src":14,"toll":false},{"cost":3.672914981842041,"dst":13,"src":14,"toll":true},{"cost":35.0,"dst":15,"src":14,"toll":false},{"cost":6.287590503692627,"dst":19,"src":14,"toll":false},{"cost":21.432605743408203,"dst":10,"src":15,"toll":false},{"cost":35.0,"dst":14,"src":15,"toll":false},{"cost":21.192859649658203,"dst":20,"src":15,"toll":false},{"cost":12.825233459472656,"dst":11,"src":16,"toll":false},{"cost":18.39487075805664,"dst":17,"src":16,"toll":false},{"cost":3.449303150177002,"dst":21,"src":16,"toll":true},{"cost":35.0,"dst":12,"src":17,"toll":false},{"cost":18.39487075805664,"dst":16,"src":17,"toll":false},{"cost":27.69989585876465,"dst":18,"src":17,"toll":false},{"cost":8.15719985961914,"dst":22,"src":17,"toll":false},{"cost":2.887437582015991,"dst":13,"src":18,"toll":true},{"cost":27.69989585876465,"dst":17,"src":18,"toll":false},{"cost":33.971038818359375,"dst":19,"src":18,"toll":false},{"cost":5.422867774963379,"dst":23,"src":18,"toll":true},{"cost":6.287590503692627,"dst":14,"src":19,"toll":false},{"cost":33.971038818359375,"dst":18,"src":19,"toll":false},{"cost":30.835161209106445,"dst":20,"src":19,"toll":false},{"cost":12.248504638671875,"dst":24,"src":19,"toll":true},{"cost":21.192859649658203,"dst":15,"src":20,"toll":false},{"cost":30.835161209106445,"dst":19,"src":20,"toll":false},{"cost":8.423065185546875,"dst":25,"src":20,"toll":false},{"cost":3.449303150177002,"dst":16,"src":21,"toll":true},{"cost":16.610126495361328,"dst":22,"src":21,"toll":false},{"cost":18.97216796875,"dst":26,"src":21,"toll":false},{"cost":8.15719985961914,"dst":17,"src":22,"toll":false},{"cost":16.610126495361328,"dst":21,"src":22,"toll":false},{"cost":7.509681224822998,"dst":23,"src":22,"toll":true},{"cost":35.0,"dst":27,"src":22,"toll":false},{"cost":5.422867774963379,"dst":18,"src":23,"toll":true},{"cost":7.509681224822998,"dst":22,"src":23,"toll":true},{"cost":10.08161449432373,"dst":24,"src":23,"toll":false},{"cost":5.659505844116211,"dst":28,"src":23,"toll":true},{"cost":12.248504638671875,"dst":19,"src":24,"toll":true},{"cost":10.08161449432373,"dst":23,"src":24,"toll":false},{"cost":35.0,"dst":25,"src":24,"toll":false},{"cost":17.5,"dst":29,"src":24,"toll":true},{"cost":8.423065185546875,"dst":20,"src":25,"toll":false},{"cost":35.0,"dst":24,"src":25,"toll":false},{"cost":24.65618324279785,"dst":30,"src":25,"toll":false},{"cost":18.97216796875,"dst":21,"src":26,"toll":false},{"cost":35.0,"dst":27,"src":26,"toll":false},{"cost":10.468877792358398,"dst":31,"src":26,"toll":false},{"cost":35.0,"dst":22,"src":27,"toll":false},{"cost":35.0,"dst":26,"src":27,"toll":false},{"cost":28.19582748413086,"dst":28,"src":27,"toll":false},{"cost":35.0,"dst":32,"src":27,"toll":false},{"cost":5.659505844116211,"dst":23,"src":28,"toll":true},{"cost":28.19582748413086,"dst":27,"src":28,"toll":false},{"cost":10.175422668457031,"dst":29,"src":28,"toll":true},{"cost":35.0,"dst":33,"src":28,"toll":false},{"cost":17.5,"dst":24,"src":29,"toll":true},{"cost":10.175422668457031,"dst":28,"src":29,"toll":true},{"cost":34.59393310546875,"dst":30,"src":29,"toll":false},{"cost":10.26406478881836,"dst":34,"src":29,"toll":true},{"cost":24.65618324279785,"dst":25,"src":30,"toll":false},{"cost":34.59393310546875,"dst":29,"src":30,"toll":false},{"cost":34.711891174316406,"dst":35,"src":30,"toll":false},{"cost":10.468877792358398,"dst":26,"src":31,"toll":false},{"cost":27.34206199645996,"dst":32,"src":31,"toll":false},{"cost":13.500520706176758,"dst":36,"src":31,"toll":true},{"cost":35.0,"dst":27,"src":32,"toll":false},{"cost":27.34206199645996,"dst":31,"src":32,"toll":false},{"cost":28.083690643310547,"dst":33,"src":32,"toll":false},{"cost":26.197847366333008,"dst":37,"src":32,"toll":false},{"cost":35.0,"dst":28,"src":33,"toll":false},{"cost":28.083690643310547,"dst":32,"src":33,"toll":false},{"cost":16.124996185302734,"dst":34,"src":33,"toll":false},{"cost":10.075279235839844,"dst":38,"src":33,"toll":false},{"cost":10.26406478881836,"dst":29,"src":34,"toll":true},{"cost":16.124996185302734,"dst":33,"src":34,"toll":false},{"cost":28.90332794189453,"dst":35,"src":34,"toll":false},{"cost":4.038092613220215,"dst":39,"src":34,"toll":true},{"cost":34.711891174316406,"dst":30,"src":35,"toll":false},{"cost":28.90332794189453,"dst":34,"src":35,"toll":false},{"cost":33.45782470703125,"dst":40,"src":35,"toll":false},{"cost":13.500520706176758,"dst":31,"src":36,"toll":true},{"cost":35.0,"dst":37,"src":36,"toll":false},{"cost":18.550853729248047,"dst":41,"src":36,"toll":false},{"cost":26.197847366333008,"dst":32,"src":37,"toll":false},{"cost":35.0,"dst":36,"src":37,"toll":false},{"cost":15.007512092590332,"dst":38,"src":37,"toll":false},{"cost":13.597450256347656,"dst":42,"src":37,"toll":false},{"cost":10.075279235839844,"dst":33,"src":38,"toll":false},{"cost":15.007512092590332,"dst":37,"src":38,"toll":false},{"cost":5.173360347747803,"dst":39,"src":38,"toll":false},{"cost":35.0,"dst":43,"src":38,"toll":false},{"cost":4.038092613220215,"dst":34,"src":39,"toll":true},{"cost":5.173360347747803,"dst":38,"src":39,"toll":false},{"cost":9.953386306762695,"dst":40,"src":39,"toll":true},{"cost":8.852142333984375,"dst":44,"src":39,"toll":true},{"cost":33.45782470703125,"dst":35,"src":40,"toll":false},{"cost":9.953386306762695,"dst":39,"src":40,"toll":true},{"cost":19.066768646240234,"dst":45,"src":40,"toll":false},{"cost":18.550853729248047,"dst":36,"src":41,"toll":false},{"cost":28.218435287475586,"dst":42,"src":41,"toll":false},{"cost":17.596664428710938,"dst":46,"src":41,"toll":false},{"cost":13.597450256347656,"dst":37,"src":42,"toll":false},{"cost":28.218435287475586,"dst":41,"src":42,"toll":false},{"cost":35.0,"dst":43,"src":42,"toll":false},{"cost":12.147600173950195,"dst":47,"src":42,"toll":false},{"cost":35.0,"dst":38,"src":43,"toll":false},{"cost":35.0,"dst":42,"src":43,"toll":false},{"cost":20.87055778503418,"dst":44,"src":43,"toll":false},{"cost":25.20032501220703,"dst":48,"src":43,"toll":false},{"cost":8.852142333984375,"dst":39,"src":44,"toll":true},{"cost":20.87055778503418,"dst":43,"src":44,"toll":false},{"cost":13.050196647644043,"dst":45,"src":44,"toll":true},{"cost":35.0,"dst":49,"src":44,"toll":false},{"cost":19.066768646240234,"dst":40,"src":45,"toll":false},{"cost":13.050196647644043,"dst":44,"src":45,"toll":true},{"cost":35.0,"dst":50,"src":45,"toll":false},{"cost":17.596664428710938,"dst":41,"src":46,"toll":false},{"cost":15.794456481933594,"dst":47,"src":46,"toll":false},{"cost":13.217352867126465,"dst":51,"src":46,"toll":false},{"cost":12.147600173950195,"dst":42,"src":47,"toll":false},{"cost":15.794456481933594,"dst":46,"src":47,"toll":false},{"cost":34.63365936279297,"dst":48,"src":47,"toll":false},{"cost":24.238998413085938,"dst":52,"src":47,"toll":false},{"cost":25.20032501220703,"dst":43,"src":48,"toll":false},{"cost":34.63365936279297,"dst":47,"src":48,"toll":false},{"cost":26.24042320251465,"dst":49,"src":48,"toll":false},{"cost":6.146500110626221,"dst":53,"src":48,"toll":true},{"cost":35.0,"dst":44,"src":49,"toll":false},{"cost":26.24042320251465,"dst":48,"src":49,"toll":false},{"cost":23.376419067382813,"dst":50,"src":49,"toll":false},{"cost":35.0,"dst":54,"src":49,"toll":false},{"cost":35.0,"dst":45,"src":50,"toll":false},{"cost":23.376419067382813,"dst":49,"src":50,"toll":false},{"cost":12.043832778930664,"dst":55,"src":50,"toll":false},{"cost":13.217352867126465,"dst":46,"src":51,"toll":false},{"cost":17.5,"dst":52,"src":51,"toll":true},{"cost":35.0,"dst":56,"src":51,"toll":false},{"cost":24.238998413085938,"dst":47,"src":52,"toll":false},{"cost":17.5,"dst":51,"src":52,"toll":true},{"cost":7.397543907165527,"dst":53,"src":52,"toll":false},{"cost":35.0,"dst":57,"src":52,"toll":false},{"cost":6.146500110626221,"dst":48,"src":53,"toll":true},{"cost":7.397543907165527,"dst":52,"src":53,"toll":false},{"cost":35.0,"dst":54,"src":53,"toll":false},{"cost":25.199909210205078,"dst":58,"src":53,"toll":false},{"cost":35.0,"dst":49,"src":54,"toll":false},{"cost":35.0,"dst":53,"src":54,"toll":false},{"cost":15.635435104370117,"dst":55,"src":54,"toll":true},{"cost":12.345320701599121,"dst":59,"src":54,"toll":true},{"cost":12.043832778930664,"dst":50,"src":55,"toll":false},{"cost":15.635435104370117,"dst":54,"src":55,"toll":true},{"cost":25.89535140991211,"dst":60,"src":55,"toll":false},{"cost":35.0,"dst":51,"src":56,"toll":false},{"cost":32.06624984741211,"dst":57,"src":56,"toll":false},{"cost":35.0,"dst":52,"src":57,"toll":false},{"cost":32.06624984741211,"dst":56,"src":57,"toll":false},{"cost":24.734586715698242,"dst":58,"src":57,"toll":false},{"cost":25.199909210205078,"dst":53,"src":58,"toll":false},{"cost":24.734586715698242,"dst":57,"src":58,"toll":false},{"cost":28.137035369873047,"dst":59,"src":58,"toll":false},{"cost":12.345320701599121,"dst":54,"src":59,"toll":true},{"cost":28.137035369873047,"dst":58,"src":59,"toll":false},{"cost":35.0,"dst":60,"src":59,"toll":false},{"cost":25.89535140991211,"dst":55,"src":60,"toll":false},{"cost":35.0,"dst":59,"src":60,"toll":false}],"K":[{"demand":60.819664001464844,"dest":29,"index":1,"orig":3},{"demand":80.46035766601563,"dest":36,"index":2,"orig":27},{"demand":8.472135543823242,"dest":12,"index":3,"orig":49},{"demand":80.91768646240234,"dest":60,"index":4,"orig":32},{"demand":73.52915954589844,"dest":44,"index":5,"orig":27},{"demand":63.377315521240234,"dest":53,"index":6,"orig":7},{"demand":60.887447357177734,"dest":6,"index":7,"orig":40},{"demand":49.235130310058594,"dest":48,"index":8,"orig":58},{"demand":77.60900115966797,"dest":55,"index":9,"orig":46},{"demand":5.973358154296875,"dest":31,"index":10,"orig":44},{"demand":25.33353042602539,"dest":7,"index":11,"orig":19},{"demand":98.30236053466797,"dest":22,"index":12,"orig":3},{"demand":49.95074462890625,"dest":31,"index":13,"orig":48},{"demand":48.026981353759766,"dest":5,"index":14,"orig":16},{"demand":33.2734489440918,"dest":8,"index":15,"orig":40},{"demand":97.22733306884766,"dest":45,"index":16,"orig":60},{"demand":22.2755126953125,"dest":16,"index":17,"orig":18},{"demand":2.7753090858459473,"dest":31,"index":18,"orig":54},{"demand":78.28199768066406,"dest":16,"index":19,"orig":24},{"demand":46.16054153442383,"dest":37,"index":20,"orig":60},{"demand":45.88899612426758,"dest":18,"index":21,"orig":49},{"demand":58.52373504638672,"dest":57,"index":22,"orig":43},{"demand":42.25099182128906,"dest":1,"index":23,"orig":41},{"demand":81.94998931884766,"dest":12,"index":24,"orig":6},{"demand":11.389376640319824,"dest":37,"index":25,"orig":42},{"demand":53.76365280151367,"dest":29,"index":26,"orig":47},{"demand":13.105315208435059,"dest":4,"index":27,"orig":34},{"demand":18.47690200805664,"dest":8,"index":28,"orig":6},{"demand":15.242232322692871,"dest":30,"index":29,"orig":1},{"demand":92.36201477050781,"dest":39,"index":30,"orig":53},{"demand":60.17509078979492,"dest":18,"index":31,"orig":20},{"demand":8.705364227294922,"dest":32,"index":32,"orig":2},{"demand":21.41542625427246,"dest":1,"index":33,"orig":8},{"demand":44.88195037841797,"dest":30,"index":34,"orig":53},{"demand":1.3735250234603882,"dest":16,"index":35,"orig":45}],"V":60}}