{"problem":{"A":[{"cost":35.0,"dst":2,"src":1,"toll":false},{"cost":35.0,"dst":13,"src":1,"toll":false},{"cost":35.0,"dst":1,"src":2,"toll":false},{"cost":30.09388542175293,"dst":3,"src":2,"toll":false},{"cost":34.272884368896484,"dst":14,"src":2,"toll":false},{"cost":30.09388542175293,"dst":2,"src":3,"toll":false},{"cost":9.971550941467285,"dst":4,"src":3,"toll":false},{"cost":22.074914932250977,"dst":15,"src":3,"toll":false},{"cost":9.971550941467285,"dst":3,"src":4,"toll":false},{"cost":9.517539978027344,"dst":5,"src":4,"toll":false},{"cost":18.598735809326172,"dst":16,"src":4,"toll":false},{"cost":9.517539978027344,"dst":4,"src":5,"toll":false},{"cost":26.000324249267578,"dst":6,"src":5,"toll":false},{"cost":35.0,"dst":17,"src":5,"toll":false},{"cost":26.000324249267578,"dst":5,"src":6,"toll":false},{"cost":32.35567855834961,"dst":7,"src":6,"toll":false},{"cost":15.25389289855957,"dst":18,"src":6,"toll":false},{"cost":32.35567855834961,"dst":6,"src":7,"toll":false},{"cost":33.68975830078125,"dst":8,"src":7,"toll":false},{"cost":20.26883316040039,"dst":19,"src":7,"toll":false},{"cost":33.68975830078125,"dst":7,"src":8,"toll":false},{"cost":35.0,"dst":9,"src":8,"toll":false},{"cost":3.1850051879882813,"dst":20,"src":8,"toll":true},{"cost":35.0,"dst":8,"src":9,"toll":false},{"cost":11.228545188903809,"dst":10,"src":9,"toll":false},{"cost":6.313119888305664,"dst":21,"src":9,"toll":false},{"cost":11.228545188903809,"dst":9,"src":10,"toll":false},{"cost":20.205398559570313,"dst":11,"src":10,"toll":false},{"cost":17.813941955566406,"dst":22,"src":10,"toll":false},{"cost":20.205398559570313,"dst":10,"src":11,"toll":false},{"cost":27.51944923400879,"dst":12,"src":11,"toll":false},{"cost":35.0,"dst":23,"src":11,"toll":false},{"cost":27.51944923400879,"dst":11,"src":12,"toll":false},{"cost":5.109825134277344,"dst":24,"src":12,"toll":false},{"cost":35.0,"dst":1,"src":13,"toll":false},{"cost":4.898326396942139,"dst":14,"src":13,"toll":true},{"cost":13.718842506408691,"dst":25,"src":13,"toll":false},{"cost":34.272884368896484,"dst":2,"src":14,"toll":false},{"cost":4.898326396942139,"dst":13,"src":14,"toll":true},{"cost":15.489351272583008,"dst":15,"src":14,"toll":false},{"cost":3.5422720909118652,"dst":26,"src":14,"toll":true},{"cost":22.074914932250977,"dst":3,"src":15,"toll":false},{"cost":15.489351272583008,"dst":14,"src":15,"toll":false},{"cost":14.713983535766602,"dst":16,"src":15,"toll":false},{"cost":35.0,"dst":27,"src":15,"toll":false},{"cost":18.598735809326172,"dst":4,"src":16,"toll":false},{"cost":14.713983535766602,"dst":15,"src":16,"toll":false},{"cost":30.66030502319336,"dst":17,"src":16,"toll":false},{"cost":9.331745147705078,"dst":28,"src":16,"toll":true},{"cost":35.0,"dst":5,"src":17,"toll":false},{"cost":30.66030502319336,"dst":16,"src":17,"toll":false},{"cost":6.7955169677734375,"dst":18,"src":17,"toll":true},{"cost":24.37454605102539,"dst":29,"src":17,"toll":false},{"cost":15.25389289855957,"dst":6,"src":18,"toll":false},{"cost":6.7955169677734375,"dst":17,"src":18,"toll":true},{"cost":21.85813331604004,"dst":19,"src":18,"toll":false},{"cost":31.571504592895508,"dst":30,"src":18,"toll":false},{"cost":20.26883316040039,"dst":7,"src":19,"toll":false},{"cost":21.85813331604004,"dst":18,"src":19,"toll":false},{"cost":9.942598342895508,"dst":20,"src":19,"toll":false},{"cost":35.0,"dst":31,"src":19,"toll":false},{"cost":3.1850051879882813,"dst":8,"src":20,"toll":true},{"cost":9.942598342895508,"dst":19,"src":20,"toll":false},{"cost":28.244571685791016,"dst":21,"src":20,"toll":false},{"cost":33.961395263671875,"dst":32,"src":20,"toll":false},{"cost":6.313119888305664,"dst":9,"src":21,"toll":false},{"cost":28.244571685791016,"dst":20,"src":21,"toll":false},{"cost":35.0,"dst":22,"src":21,"toll":false},{"cost":29.913808822631836,"dst":33,"src":21,"toll":false},{"cost":17.813941955566406,"dst":10,"src":22,"toll":false},{"cost":35.0,"dst":21,"src":22,"toll":false},{"cost":34.49112319946289,"dst":23,"src":22,"toll":false},{"cost":6.167571067810059,"dst":34,"src":22,"toll":false},{"cost":35.0,"dst":11,"src":23,"toll":false},{"cost":34.49112319946289,"dst":22,"src":23,"toll":false},{"cost":35.0,"dst":24,"src":23,"toll":false},{"cost":30.211694717407227,"dst":35,"src":23,"toll":false},{"cost":5.109825134277344,"dst":12,"src":24,"toll":false},{"cost":35.0,"dst":23,"src":24,"toll":false},{"cost":20.137943267822266,"dst":36,"src":24,"toll":false},{"cost":13.718842506408691,"dst":13,"src":25,"toll":false},{"cost":25.962535858154297,"dst":26,"src":25,"toll":false},{"cost":23.31591033935547,"dst":37,"src":25,"toll":false},{"cost":3.5422720909118652,"dst":14,"src":26,"toll":true},{"cost":25.962535858154297,"dst":25,"src":26,"toll":false},{"cost":35.0,"dst":27,"src":26,"toll":false},{"cost":16.714204788208008,"dst":38,"src":26,"toll":true},{"cost":35.0,"dst":15,"src":27,"toll":false},{"cost":35.0,"dst":26,"src":27,"toll":false},{"cost":25.424108505249023,"dst":28,"src":27,"toll":false},{"cost":4.150979042053223,"dst":39,"src":27,"toll":true},{"cost":9.331745147705078,"dst":16,"src":28,"toll":true},{"cost":25.424108505249023,"dst":27,"src":28,"toll":false},{"cost":34.05992889404297,"dst":29,"src":28,"toll":false},{"cost":5.396726608276367,"dst":40,"src":28,"toll":true},{"cost":24.37454605102539,"dst":17,"src":29,"toll":false},{"cost":34.05992889404297,"dst":28,"src":29,"toll":false},{"cost":7.297029972076416,"dst":30,"src":29,"toll":true},{"cost":26.125383377075195,"dst":41,"src":29,"toll":false},{"cost":31.571504592895508,"dst":18,"src":30,"toll":false},{"cost":7.297029972076416,"dst":29,"src":30,"toll":true},{"cost":35.0,"dst":31,"src":30,"toll":false},{"cost":5.198662757873535,"dst":42,"src":30,"toll":true},{"cost":35.0,"dst":19,"src":31,"toll":false},{"cost":35.0,"dst":30,"src":31,"toll":false},{"cost":10.0068359375,"dst":32,"src":31,"toll":false},{"cost":29.571815490722656,"dst":43,"src":31,"toll":false},{"cost":33.961395263671875,"dst":20,"src":32,"toll":false},{"cost":10.0068359375,"dst":31,"src":32,"toll":false},{"cost":34.76597213745117,"dst":33,"src":32,"toll":false},{"cost":7.0839715003967285,"dst":44,"src":32,"toll":false},{"cost":29.913808822631836,"dst":21,"src":33,"toll":false},{"cost":34.76597213745117,"dst":32,"src":33,"toll":false},{"cost":6.911369323730469,"dst":34,"src":33,"toll":false},{"cost":24.58932876586914,"dst":45,"src":33,"toll":false},{"cost":6.167571067810059,"dst":22,"src":34,"toll":false},{"cost":6.911369323730469,"dst":33,"src":34,"toll":false},{"cost":27.365516662597656,"dst":35,"src":34,"toll":false},{"cost":7.94077730178833,"dst":46,"src":34,"toll":true},{"cost":30.211694717407227,"dst":23,"src":35,"toll":false},{"cost":27.365516662597656,"dst":34,"src":35,"toll":false},{"cost":10.49478530883789,"dst":36,"src":35,"toll":false},{"cost":14.338910102844238,"dst":47,"src":35,"toll":false},{"cost":20.137943267822266,"dst":24,"src":36,"toll":false},{"cost":10.49478530883789,"dst":35,"src":36,"toll":false},{"cost":12.160015106201172,"dst":48,"src":36,"toll":false},{"cost":23.31591033935547,"dst":25,"src":37,"toll":false},{"cost":26.38585090637207,"dst":38,"src":37,"toll":false},{"cost":35.0,"dst":49,"src":37,"toll":false},{"cost":16.714204788208008,"dst":26,"src":38,"toll":true},{"cost":26.38585090637207,"dst":37,"src":38,"toll":false},{"cost":20.730310440063477,"dst":39,"src":38,"toll":false},{"cost":16.956836700439453,"dst":50,"src":38,"toll":true},{"cost":4.150979042053223,"dst":27,"src":39,"toll":true},{"cost":20.730310440063477,"dst":38,"src":39,"toll":false},{"cost":23.878158569335938,"dst":40,"src":39,"toll":false},{"cost":35.0,"dst":51,"src":39,"toll":false},{"cost":5.396726608276367,"dst":28,"src":40,"toll":true},{"cost":23.878158569335938,"dst":39,"src":40,"toll":false},{"cost":35.0,"dst":41,"src":40,"toll":false},{"cost":34.22917175292969,"dst":52,"src":40,"toll":false},{"cost":26.125383377075195,"dst":29,"src":41,"toll":false},{"cost":35.0,"dst":40,"src":41,"toll":false},{"cost":35.0,"dst":42,"src":41,"toll":false},{"cost":20.150665283203125,"dst":53,"src":41,"toll":false},{"cost":5.198662757873535,"dst":30,"src":42,"toll":true},{"cost":35.0,"dst":41,"src":42,"toll":false},{"cost":13.818530082702637,"dst":43,"src":42,"toll":false},{"cost":27.329694747924805,"dst":54,"src":42,"toll":false},{"cost":29.571815490722656,"dst":31,"src":43,"toll":false},{"cost":13.818530082702637,"dst":42,"src":43,"toll":false},{"cost":3.4732789993286133,"dst":44,"src":43,"toll":true},{"cost":7.286038398742676,"dst":55,"src":43,"toll":true},{"cost":7.0839715003967285,"dst":32,"src":44,"toll":false},{"cost":3.4732789993286133,"dst":43,"src":44,"toll":true},{"cost":5.644080638885498,"dst":45,"src":44,"toll":false},{"cost":31.283584594726563,"dst":56,"src":44,"toll":false},{"cost":24.58932876586914,"dst":33,"src":45,"toll":false},{"cost":5.644080638885498,"dst":44,"src":45,"toll":false},{"cost":5.46015739440918,"dst":46,"src":45,"toll":true},{"cost":5.223628520965576,"dst":57,"src":45,"toll":true},{"cost":7.94077730178833,"dst":34,"src":46,"toll":true},{"cost":5.46015739440918,"dst":45,"src":46,"toll":true},{"cost":24.730566024780273,"dst":47,"src":46,"toll":false},{"cost":18.0992431640625,"dst":58,"src":46,"toll":false},{"cost":14.338910102844238,"dst":35,"src":47,"toll":false},{"cost":24.730566024780273,"dst":46,"src":47,"toll":false},{"cost":28.2749080657959,"dst":48,"src":47,"toll":false},{"cost":11.696194648742676,"dst":59,"src":47,"toll":true},{"cost":12.160015106201172,"dst":36,"src":48,"toll":false},{"cost":28.2749080657959,"dst":47,"src":48,"toll":false},{"cost":35.0,"dst":60,"src":48,"toll":false},{"cost":35.0,"dst":37,"src":49,"toll":false},{"cost":9.517294883728027,"dst":50,"src":49,"toll":true},{"cost":32.588584899902344,"dst":61,"src":49,"toll":false},{"cost":16.956836700439453,"dst":38,"src":50,"toll":true},{"cost":9.517294883728027,"dst":49,"src":50,"toll":true},{"cost":35.0,"dst":51,"src":50,"toll":false},{"cost":11.20977783203125,"dst":62,"src":50,"toll":true},{"cost":35.0,"dst":39,"src":51,"toll":false},{"cost":35.0,"dst":50,"src":51,"toll":false},{"cost":35.0,"dst":52,"src":51,"toll":false},{"cost":4.053802013397217,"dst":63,"src":51,"toll":true},{"cost":34.22917175292969,"dst":40,"src":52,"toll":false},{"cost":35.0,"dst":51,"src":52,"toll":false},{"cost":9.772994995117188,"dst":53,"src":52,"toll":true},{"cost":35.0,"dst":64,"src":52,"toll":false},{"cost":20.150665283203125,"dst":41,"src":53,"toll":false},{"cost":9.772994995117188,"dst":52,"src":53,"toll":true},{"cost":19.27783966064453,"dst":54,"src":53,"toll":false},{"cost":15.092536926269531,"dst":65,"src":53,"toll":true},{"cost":27.329694747924805,"dst":42,"src":54,"toll":false},{"cost":19.27783966064453,"dst":53,"src":54,"toll":false},{"cost":9.52828598022461,"dst":55,"src":54,"toll":false},{"cost":14.78723430633545,"dst":66,"src":54,"toll":true},{"cost":7.286038398742676,"dst":43,"src":55,"toll":true},{"cost":9.52828598022461,"dst":54,"src":55,"toll":false},{"cost":7.875165939331055,"dst":56,"src":55,"toll":false},{"cost":33.43016052246094,"dst":67,"src":55,"toll":false},{"cost":31.283584594726563,"dst":44,"src":56,"toll":false},{"cost":7.875165939331055,"dst":55,"src":56,"toll":false},{"cost":5.5139617919921875,"dst":57,"src":56,"toll":true},{"cost":35.0,"dst":68,"src":56,"toll":false},{"cost":5.223628520965576,"dst":45,"src":57,"toll":true},{"cost":5.5139617919921875,"dst":56,"src":57,"toll":true},{"cost":35.0,"dst":58,"src":57,"toll":false},{"cost":35.0,"dst":69,"src":57,"toll":false},{"cost":18.0992431640625,"dst":46,"src":58,"toll":false},{"cost":35.0,"dst":57,"src":58,"toll":false},{"cost":30.245967864990234,"dst":59,"src":58,"toll":false},{"cost":6.829890727996826,"dst":70,"src":58,"toll":true},{"cost":11.696194648742676,"dst":47,"src":59,"toll":true},{"cost":30.245967864990234,"dst":58,"src":59,"toll":false},{"cost":16.50377655029297,"dst":60,"src":59,"toll":false},{"cost":3.1330959796905518,"dst":71,"src":59,"toll":true},{"cost":35.0,"dst":48,"src":60,"toll":false},{"cost":16.50377655029297,"dst":59,"src":60,"toll":false},{"cost":28.922401428222656,"dst":72,"src":60,"toll":false},{"cost":32.588584899902344,"dst":49,"src":61,"toll":false},{"cost":35.0,"dst":62,"src":61,"toll":false},{"cost":30.715084075927734,"dst":73,"src":61,"toll":false},{"cost":11.20977783203125,"dst":50,"src":62,"toll":true},{"cost":35.0,"dst":61,"src":62,"toll":false},{"cost":16.340431213378906,"dst":63,"src":62,"toll":false},{"cost":10.216974258422852,"dst":74,"src":62,"toll":true},{"cost":4.053802013397217,"dst":51,"src":63,"toll":true},{"cost":16.340431213378906,"dst":62,"src":63,"toll":false},{"cost":24.6672306060791,"dst":64,"src":63,"toll":false},{"cost":9.382061004638672,"dst":75,"src":63,"toll":true},{"cost":35.0,"dst":52,"src":64,"toll":false},{"cost":24.6672306060791,"dst":63,"src":64,"toll":false},{"cost":35.0,"dst":65,"src":64,"toll":false},{"cost":35.0,"dst":76,"src":64,"toll":false},{"cost":15.092536926269531,"dst":53,"src":65,"toll":true},{"cost":35.0,"dst":64,"src":65,"toll":false},{"cost":19.627254486083984,"dst":66,"src":65,"toll":false},{"cost":4.731311798095703,"dst":77,"src":65,"toll":true},{"cost":14.78723430633545,"dst":54,"src":66,"toll":true},{"cost":19.627254486083984,"dst":65,"src":66,"toll":false},{"cost":35.0,"dst":67,"src":66,"toll":false},{"cost":21.83085060119629,"dst":78,"src":66,"toll":false},{"cost":33.43016052246094,"dst":55,"src":67,"toll":false},{"cost":35.0,"dst":66,"src":67,"toll":false},{"cost":31.076772689819336,"dst":68,"src":67,"toll":false},{"cost":35.0,"dst":79,"src":67,"toll":false},{"cost":35.0,"dst":56,"src":68,"toll":false},{"cost":31.076772689819336,"dst":67,"src":68,"toll":false},{"cost":24.456911087036133,"dst":69,"src":68,"toll":false},{"cost":10.35661506652832,"dst":80,"src":68,"toll":false},{"cost":35.0,"dst":57,"src":69,"toll":false},{"cost":24.456911087036133,"dst":68,"src":69,"toll":false},{"cost":20.20943832397461,"dst":70,"src":69,"toll":false},{"cost":12.087858200073242,"dst":81,"src":69,"toll":false},{"cost":6.829890727996826,"dst":58,"src":70,"toll":true},{"cost":20.20943832397461,"dst":69,"src":70,"toll":false},{"cost":26.88633918762207,"dst":71,"src":70,"toll":false},{"cost":28.031814575195313,"dst":82,"src":70,"toll":false},{"cost":3.1330959796905518,"dst":59,"src":71,"toll":true},{"cost":26.88633918762207,"dst":70,"src":71,"toll":false},{"cost":35.0,"dst":72,"src":71,"toll":false},{"cost":4.181771755218506,"dst":83,"src":71,"toll":true},{"cost":28.922401428222656,"dst":60,"src":72,"toll":false},{"cost":35.0,"dst":71,"src":72,"toll":false},{"cost":30.015338897705078,"dst":84,"src":72,"toll":false},{"cost":30.715084075927734,"dst":61,"src":73,"toll":false},{"cost":9.02900505065918,"dst":74,"src":73,"toll":false},{"cost":17.5,"dst":85,"src":73,"toll":true},{"cost":10.216974258422852,"dst":62,"src":74,"toll":true},{"cost":9.02900505065918,"dst":73,"src":74,"toll":false},{"cost":6.858473300933838,"dst":75,"src":74,"toll":true},{"cost":3.4961109161376953,"dst":86,"src":74,"toll":true},{"cost":9.382061004638672,"dst":63,"src":75,"toll":true},{"cost":6.858473300933838,"dst":74,"src":75,"toll":true},{"cost":35.0,"dst":76,"src":75,"toll":false},{"cost":32.46037673950195,"dst":87,"src":75,"toll":false},{"cost":35.0,"dst":64,"src":76,"toll":false},{"cost":35.0,"dst":75,"src":76,"toll":false},{"cost":13.522610664367676,"dst":77,"src":76,"toll":false},{"cost":16.128822326660156,"dst":88,"src":76,"toll":false},{"cost":4.731311798095703,"dst":65,"src":77,"toll":true},{"cost":13.522610664367676,"dst":76,"src":77,"toll":false},{"cost":16.221216201782227,"dst":78,"src":77,"toll":false},{"cost":28.45389175415039,"dst":89,"src":77,"toll":false},{"cost":21.83085060119629,"dst":66,"src":78,"toll":false},{"cost":16.221216201782227,"dst":77,"src":78,"toll":false},{"cost":6.869826316833496,"dst":79,"src":78,"toll":false},{"cost":23.11899757385254,"dst":90,"src":78,"toll":false},{"cost":35.0,"dst":67,"src":79,"toll":false},{"cost":6.869826316833496,"dst":78,"src":79,"toll":false},{"cost":20.964691162109375,"dst":80,"src":79,"toll":false},{"cost":22.11431884765625,"dst":91,"src":79,"toll":false},{"cost":10.35661506652832,"dst":68,"src":80,"toll":false},{"cost":20.964691162109375,"dst":79,"src":80,"toll":false},{"cost":35.0,"dst":81,"src":80,"toll":false},{"cost":15.013818740844727,"dst":92,"src":80,"toll":false},{"cost":12.087858200073242,"dst":69,"src":81,"toll":false},{"cost":35.0,"dst":80,"src":81,"toll":false},{"cost":35.0,"dst":82,"src":81,"toll":false},{"cost":28.339641571044922,"dst":93,"src":81,"toll":false},{"cost":28.031814575195313,"dst":70,"src":82,"toll":false},{"cost":35.0,"dst":81,"src":82,"toll":false},{"cost":33.97201156616211,"dst":83,"src":82,"toll":false},{"cost":35.0,"dst":94,"src":82,"toll":false},{"cost":4.181771755218506,"dst":71,"src":83,"toll":true},{"cost":33.97201156616211,"dst":82,"src":83,"toll":false},{"cost":35.0,"dst":84,"src":83,"toll":false},{"cost":33.65113067626953,"dst":95,"src":83,"toll":false},{"cost":30.015338897705078,"dst":72,"src":84,"toll":false},{"cost":35.0,"dst":83,"src":84,"toll":false},{"cost":9.943719863891602,"dst":96,"src":84,"toll":true},{"cost":17.5,"dst":73,"src":85,"toll":true},{"cost":13.307022094726563,"dst":86,"src":85,"toll":false},{"cost":34.40085220336914,"dst":97,"src":85,"toll":false},{"cost":3.4961109161376953,"dst":74,"src":86,"toll":true},{"cost":13.307022094726563,"dst":85,"src":86,"toll":false},{"cost":19.293123245239258,"dst":87,"src":86,"toll":false},{"cost":7.52610969543457,"dst":98,"src":86,"toll":true},{"cost":32.46037673950195,"dst":75,"src":87,"toll":false},{"cost":19.293123245239258,"dst":86,"src":87,"toll":false},{"cost":29.9472599029541,"dst":88,"src":87,"toll":false},{"cost":27.333843231201172,"dst":99,"src":87,"toll":false},{"cost":16.128822326660156,"dst":76,"src":88,"toll":false},{"cost":29.9472599029541,"dst":87,"src":88,"toll":false},{"cost":35.0,"dst":89,"src":88,"toll":false},{"cost":35.0,"dst":100,"src":88,"toll":false},{"cost":28.45389175415039,"dst":77,"src":89,"toll":false},{"cost":35.0,"dst":88,"src":89,"toll":false},{"cost":35.0,"dst":90,"src":89,"toll":false},{"cost":22.231956481933594,"dst":101,"src":89,"toll":false},{"cost":23.11899757385254,"dst":78,"src":90,"toll":false},{"cost":35.0,"dst":89,"src":90,"toll":false},{"cost":24.56888198852539,"dst":91,"src":90,"toll":false},{"cost":35.0,"dst":102,"src":90,"toll":false},{"cost":22.11431884765625,"dst":79,"src":91,"toll":false},{"cost":24.56888198852539,"dst":90,"src":91,"toll":false},{"cost":27.64570426940918,"dst":92,"src":91,"toll":false},{"cost":32.80052947998047,"dst":103,"src":91,"toll":false},{"cost":15.013818740844727,"dst":80,"src":92,"toll":false},{"cost":27.64570426940918,"dst":91,"src":92,"toll":false},{"cost":6.522443771362305,"dst":93,"src":92,"toll":false},{"cost":26.77843475341797,"dst":104,"src":92,"toll":false},{"cost":28.339641571044922,"dst":81,"src":93,"toll":false},{"cost":6.522443771362305,"dst":92,"src":93,"toll":false},{"cost":35.0,"dst":94,"src":93,"toll":false},{"cost":30.13930892944336,"dst":105,"src":93,"toll":false},{"cost":35.0,"dst":82,"src":94,"toll":false},{"cost":35.0,"dst":93,"src":94,"toll":false},{"cost":31.634876251220703,"dst":95,"src":94,"toll":false},{"cost":21.063596725463867,"dst":106,"src":94,"toll":false},{"cost":33.65113067626953,"dst":83,"src":95,"toll":false},{"cost":31.634876251220703,"dst":94,"src":95,"toll":false},{"cost":26.47752571105957,"dst":96,"src":95,"toll":false},{"cost":18.802778244018555,"dst":107,"src":95,"toll":false},{"cost":9.943719863891602,"dst":84,"src":96,"toll":true},{"cost":26.47752571105957,"dst":95,"src":96,"toll":false},{"cost":18.728302001953125,"dst":108,"src":96,"toll":false},{"cost":34.40085220336914,"dst":85,"src":97,"toll":false},{"cost":35.0,"dst":98,"src":97,"toll":false},{"cost":9.824533462524414,"dst":109,"src":97,"toll":false},{"cost":7.52610969543457,"dst":86,"src":98,"toll":true},{"cost":35.0,"dst":97,"src":98,"toll":false},{"cost":24.330398559570313,"dst":99,"src":98,"toll":false},{"cost":3.6998515129089355,"dst":110,"src":98,"toll":true},{"cost":27.333843231201172,"dst":87,"src":99,"toll":false},{"cost":24.330398559570313,"dst":98,"src":99,"toll":false},{"cost":21.075937271118164,"dst":100,"src":99,"toll":false},{"cost":6.992762565612793,"dst":111,"src":99,"toll":false},{"cost":35.0,"dst":88,"src":100,"toll":false},{"cost":21.075937271118164,"dst":99,"src":100,"toll":false},{"cost":20.839509963989258,"dst":101,"src":100,"toll":false},{"cost":28.515592575073242,"dst":112,"src":100,"toll":false},{"cost":22.231956481933594,"dst":89,"src":101,"toll":false},{"cost":20.839509963989258,"dst":100,"src":101,"toll":false},{"cost":15.465150833129883,"dst":102,"src":101,"toll":false},{"cost":24.0349178314209,"dst":113,"src":101,"toll":false},{"cost":35.0,"dst":90,"src":102,"toll":false},{"cost":15.465150833129883,"dst":101,"src":102,"toll":false},{"cost":18.10888671875,"dst":103,"src":102,"toll":false},{"cost":35.0,"dst":114,"src":102,"toll":false},{"cost":32.80052947998047,"dst":91,"src":103,"toll":false},{"cost":18.10888671875,"dst":102,"src":103,"toll":false},{"cost":19.724037170410156,"dst":104,"src":103,"toll":false},{"cost":27.83509635925293,"dst":115,"src":103,"toll":false},{"cost":26.77843475341797,"dst":92,"src":104,"toll":false},{"cost":19.724037170410156,"dst":103,"src":104,"toll":false},{"cost":20.913345336914063,"dst":105,"src":104,"toll":false},{"cost":35.0,"dst":116,"src":104,"toll":false},{"cost":30.13930892944336,"dst":93,"src":105,"toll":false},{"cost":20.913345336914063,"dst":104,"src":105,"toll":false},{"cost":21.40874671936035,"dst":106,"src":105,"toll":false},{"cost":11.431653022766113,"dst":117,"src":105,"toll":true},{"cost":21.063596725463867,"dst":94,"src":106,"toll":false},{"cost":21.40874671936035,"dst":105,"src":106,"toll":false},{"cost":15.538697242736816,"dst":107,"src":106,"toll":false},{"cost":35.0,"dst":118,"src":106,"toll":false},{"cost":18.802778244018555,"dst":95,"src":107,"toll":false},{"cost":15.538697242736816,"dst":106,"src":107,"toll":false},{"cost":28.326995849609375,"dst":108,"src":107,"toll":false},{"cost":8.62579345703125,"dst":119,"src":107,"toll":true},{"cost":18.728302001953125,"dst":96,"src":108,"toll":false},{"cost":28.326995849609375,"dst":107,"src":108,"toll":false},{"cost":25.829952239990234,"dst":120,"src":108,"toll":false},{"cost":9.824533462524414,"dst":97,"src":109,"toll":false},{"cost":5.315133571624756,"dst":110,"src":109,"toll":true},{"cost":29.75574493408203,"dst":121,"src":109,"toll":false},{"cost":3.6998515129089355,"dst":98,"src":110,"toll":true},{"cost":5.315133571624756,"dst":109,"src":110,"toll":true},{"cost":5.92360782623291,"dst":111,"src":110,"toll":false},{"cost":6.336856842041016,"dst":122,"src":110,"toll":true},{"cost":6.992762565612793,"dst":99,"src":111,"toll":false},{"cost":5.92360782623291,"dst":110,"src":111,"toll":false},{"cost":35.0,"dst":112,"src":111,"toll":false},{"cost":22.065065383911133,"dst":123,"src":111,"toll":false},{"cost":28.515592575073242,"dst":100,"src":112,"toll":false},{"cost":35.0,"dst":111,"src":112,"toll":false},{"cost":6.340915679931641,"dst":113,"src":112,"toll":false},{"cost":3.8051226139068604,"dst":124,"src":112,"toll":true},{"cost":24.0349178314209,"dst":101,"src":113,"toll":false},{"cost":6.340915679931641,"dst":112,"src":113,"toll":false},{"cost":22.610490798950195,"dst":114,"src":113,"toll":false},{"cost":22.659944534301758,"dst":125,"src":113,"toll":false},{"cost":35.0,"dst":102,"src":114,"toll":false},{"cost":22.610490798950195,"dst":113,"src":114,"toll":false},{"cost":18.75812339782715,"dst":115,"src":114,"toll":false},{"cost":21.503908157348633,"dst":126,"src":114,"toll":false},{"cost":27.83509635925293,"dst":103,"src":115,"toll":false},{"cost":18.75812339782715,"dst":114,"src":115,"toll":false},{"cost":35.0,"dst":116,"src":115,"toll":false},{"cost":3.9492931365966797,"dst":127,"src":115,"toll":true},{"cost":35.0,"dst":104,"src":116,"toll":false},{"cost":35.0,"dst":115,"src":116,"toll":false},{"cost":25.454416275024414,"dst":117,"src":116,"toll":false},{"cost":31.741941452026367,"dst":128,"src":116,"toll":false},{"cost":11.431653022766113,"dst":105,"src":117,"toll":true},{"cost":25.454416275024414,"dst":116,"src":117,"toll":false},{"cost":12.263925552368164,"dst":118,"src":117,"toll":false},{"cost":8.203015327453613,"dst":129,"src":117,"toll":true},{"cost":35.0,"dst":106,"src":118,"toll":false},{"cost":12.263925552368164,"dst":117,"src":118,"toll":false},{"cost":35.0,"dst":119,"src":118,"toll":false},{"cost":23.556013107299805,"dst":130,"src":118,"toll":false},{"cost":8.62579345703125,"dst":107,"src":119,"toll":true},{"cost":35.0,"dst":118,"src":119,"toll":false},{"cost":29.865211486816406,"dst":120,"src":119,"toll":false},{"cost":20.331472396850586,"dst":131,"src":119,"toll":false},{"cost":25.829952239990234,"dst":108,"src":120,"toll":false},{"cost":29.865211486816406,"dst":119,"src":120,"toll":false},{"cost":24.773897171020508,"dst":132,"src":120,"toll":false},{"cost":29.75574493408203,"dst":109,"src":121,"toll":false},{"cost":5.975781440734863,"dst":122,"src":121,"toll":false},{"cost":10.055872917175293,"dst":133,"src":121,"toll":false},{"cost":6.336856842041016,"dst":110,"src":122,"toll":true},{"cost":5.975781440734863,"dst":121,"src":122,"toll":false},{"cost":2.9146039485931396,"dst":123,"src":122,"toll":true},{"cost":10.21615982055664,"dst":134,"src":122,"toll":false},{"cost":22.065065383911133,"dst":111,"src":123,"toll":false},{"cost":2.9146039485931396,"dst":122,"src":123,"toll":true},{"cost":13.341757774353027,"dst":124,"src":123,"toll":true},{"cost":21.612009048461914,"dst":135,"src":123,"toll":false},{"cost":3.8051226139068604,"dst":112,"src":124,"toll":true},{"cost":13.341757774353027,"dst":123,"src":124,"toll":true},{"cost":2.610473155975342,"dst":125,"src":124,"toll":true},{"cost":16.87282371520996,"dst":136,"src":124,"toll":false},{"cost":22.659944534301758,"dst":113,"src":125,"toll":false},{"cost":2.610473155975342,"dst":124,"src":125,"toll":true},{"cost":4.607439994812012,"dst":126,"src":125,"toll":true},{"cost":26.977930068969727,"dst":137,"src":125,"toll":false},{"cost":21.503908157348633,"dst":114,"src":126,"toll":false},{"cost":4.607439994812012,"dst":125,"src":126,"toll":true},{"cost":5.61100959777832,"dst":127,"src":126,"toll":true},{"cost":18.63452911376953,"dst":138,"src":126,"toll":false},{"cost":3.9492931365966797,"dst":115,"src":127,"toll":true},{"cost":5.61100959777832,"dst":126,"src":127,"toll":true},{"cost":21.919157028198242,"dst":128,"src":127,"toll":false},{"cost":8.516536712646484,"dst":139,"src":127,"toll":false},{"cost":31.741941452026367,"dst":116,"src":128,"toll":false},{"cost":21.919157028198242,"dst":127,"src":128,"toll":false},{"cost":35.0,"dst":129,"src":128,"toll":false},{"cost":35.0,"dst":140,"src":128,"toll":false},{"cost":8.203015327453613,"dst":117,"src":129,"toll":true},{"cost":35.0,"dst":128,"src":129,"toll":false},{"cost":11.155641555786133,"dst":130,"src":129,"toll":false},{"cost":9.64712142944336,"dst":141,"src":129,"toll":false},{"cost":23.556013107299805,"dst":118,"src":130,"toll":false},{"cost":11.155641555786133,"dst":129,"src":130,"toll":false},{"cost":27.433551788330078,"dst":131,"src":130,"toll":false},{"cost":17.5,"dst":142,"src":130,"toll":true},{"cost":20.331472396850586,"dst":119,"src":131,"toll":false},{"cost":27.433551788330078,"dst":130,"src":131,"toll":false},{"cost":12.904119491577148,"dst":132,"src":131,"toll":true},{"cost":3.0043888092041016,"dst":143,"src":131,"toll":true},{"cost":24.773897171020508,"dst":120,"src":132,"toll":false},{"cost":12.904119491577148,"dst":131,"src":132,"toll":true},{"cost":17.5,"dst":144,"src":132,"toll":true},{"cost":10.055872917175293,"dst":121,"src":133,"toll":false},{"cost":17.5,"dst":134,"src":133,"toll":true},{"cost":10.21615982055664,"dst":122,"src":134,"toll":false},{"cost":17.5,"dst":133,"src":134,"toll":true},{"cost":30.265735626220703,"dst":135,"src":134,"toll":false},{"cost":21.612009048461914,"dst":123,"src":135,"toll":false},{"cost":30.265735626220703,"dst":134,"src":135,"toll":false},{"cost":6.490182876586914,"dst":136,"src":135,"toll":false},{"cost":16.87282371520996,"dst":124,"src":136,"toll":false},{"cost":6.490182876586914,"dst":135,"src":136,"toll":false},{"cost":24.2997989654541,"dst":137,"src":136,"toll":false},{"cost":26.977930068969727,"dst":125,"src":137,"toll":false},{"cost":24.2997989654541,"dst":136,"src":137,"toll":false},{"cost":13.52500057220459,"dst":138,"src":137,"toll":false},{"cost":18.63452911376953,"dst":126,"src":138,"toll":false},{"cost":13.52500057220459,"dst":137,"src":138,"toll":false},{"cost":24.443330764770508,"dst":139,"src":138,"toll":false},{"cost":8.516536712646484,"dst":127,"src":139,"toll":false},{"cost":24.443330764770508,"dst":138,"src":139,"toll":false},{"cost":8.993022918701172,"dst":140,"src":139,"toll":false},{"cost":35.0,"dst":128,"src":140,"toll":false},{"cost":8.993022918701172,"dst":139,"src":140,"toll":false},{"cost":35.0,"dst":141,"src":140,"toll":false},{"cost":9.64712142944336,"dst":129,"src":141,"toll":false},{"cost":35.0,"dst":140,"src":141,"toll":false},{"cost":27.556169509887695,"dst":142,"src":141,"toll":false},{"cost":17.5,"dst":130,"src":142,"toll":true},{"cost":27.556169509887695,"dst":141,"src":142,"toll":false},{"cost":5.5184197425842285,"dst":143,"src":142,"toll":false},{"cost":3.0043888092041016,"dst":131,"src":143,"toll":true},{"cost":5.5184197425842285,"dst":142,"src":143,"toll":false},{"cost":21.7179012298584,"dst":144,"src":143,"toll":false},{"cost":17.5,"dst":132,"src":144,"toll":true},{"cost":21.7179012298584,"dst":143,"src":144,"toll":false}],"K":[{"demand":62.4655876159668,"dest":25,"index":1,"orig":12},{"demand":57.14870071411133,"dest":72,"index":2,"orig":126},{"demand":74.32147216796875,"dest":104,"index":3,"orig":34},{"demand":68.03385925292969,"dest":51,"index":4,"orig":89},{"demand":81.61392211914063,"dest":44,"index":5,"orig":27},{"demand":34.19283676147461,"dest":62,"index":6,"orig":92},{"demand":50.49617385864258,"dest":56,"index":7,"orig":11},{"demand":74.84680938720703,"dest":92,"index":8,"orig":123},{"demand":3.280435562133789,"dest":39,"index":9,"orig":116},{"demand":26.299806594848633,"dest":87,"index":10,"orig":21},{"demand":22.32630729675293,"dest":135,"index":11,"orig":13},{"demand":87.57364654541016,"dest":97,"index":12,"orig":75},{"demand":36.83195495605469,"dest":96,"index":13,"orig":59},{"demand":93.63565063476563,"dest":67,"index":14,"orig":16},{"demand":48.049102783203125,"dest":2,"index":15,"orig":78},{"demand":16.93180274963379,"dest":73,"index":16,"orig":61},{"demand":50.64766311645508,"dest":125,"index":17,"orig":102},{"demand":97.17132568359375,"dest":129,"index":18,"orig":82},{"demand":2.731773853302002,"dest":25,"index":19,"orig":113},{"demand":12.541888236999512,"dest":129,"index":20,"orig":144},{"demand":26.122459411621094,"dest":32,"index":21,"orig":64},{"demand":50.11294937133789,"dest":2,"index":22,"orig":142},{"demand":14.16735553741455,"dest":122,"index":23,"orig":114},{"demand":65.77710723876953,"dest":96,"index":24,"orig":57},{"demand":99.7066879272461,"dest":130,"index":25,"orig":9},{"demand":14.615875244140625,"dest":119,"index":26,"orig":30},{"demand":18.521764755249023,"dest":65,"index":27,"orig":78},{"demand":62.1685905456543,"dest":35,"index":28,"orig":91},{"demand":33.93904495239258,"dest":5,"index":29,"orig":65},{"demand":35.355892181396484,"dest":136,"index":30,"orig":142},{"demand":29.732927322387695,"dest":7,"index":31,"orig":75},{"demand":49.26370620727539,"dest":38,"index":32,"orig":133},{"demand":80.42713165283203,"dest":16,"index":33,"orig":89},{"demand":38.872947692871094,"dest":95,"index":34,"orig":23},{"demand":84.4417724609375,"dest":14,"index":35,"orig":87},{"demand":82.95336151123047,"dest":141,"index":36,"orig":104},{"demand":73.88850402832031,"dest":2,"index":37,"orig":5},{"demand":63.819419860839844,"dest":42,"index":38,"orig":17},{"demand":80.59230041503906,"dest":13,"index":39,"orig":102},{"demand":7.744921684265137,"dest":73,"index":40,"orig":29}],"V":144}}